{"nodes": [{"id": "users_zhijian_golandprojects_juicefs_cmd_compact_go", "label": "compact.go", "file_type": "code", "source_file": "cmd/compact.go", "source_location": "L1"}, {"id": "users_zhijian_golandprojects_juicefs_cmd_compact_cmdcompact", "label": "cmdCompact()", "file_type": "code", "source_file": "cmd/compact.go", "source_location": "L30"}, {"id": "command", "label": "Command", "file_type": "code", "source_file": "", "source_location": "", "origin_file": "/Users/zhijian/GolandProjects/juicefs/cmd/compact.go"}, {"id": "users_zhijian_golandprojects_juicefs_cmd_compact_compact", "label": "compact()", "file_type": "code", "source_file": "cmd/compact.go", "source_location": "L53"}, {"id": "context", "label": "Context", "file_type": "code", "source_file": "", "source_location": "", "origin_file": "/Users/zhijian/GolandProjects/juicefs/cmd/compact.go"}, {"id": "users_zhijian_golandprojects_juicefs_cmd_compact_docompact", "label": "doCompact()", "file_type": "code", "source_file": "cmd/compact.go", "source_location": "L90"}, {"id": "ino", "label": "Ino", "file_type": "code", "source_file": "", "source_location": "", "origin_file": "/Users/zhijian/GolandProjects/juicefs/cmd/compact.go"}], "edges": [{"source": "users_zhijian_golandprojects_juicefs_cmd_compact_go", "target": "go_pkg_fmt", "relation": "imports_from", "confidence": "EXTRACTED", "source_file": "cmd/compact.go", "source_location": "L20", "weight": 1.0, "context": "import"}, {"source": "users_zhijian_golandprojects_juicefs_cmd_compact_go", "target": "go_pkg_math", "relation": "imports_from", "confidence": "EXTRACTED", "source_file": "cmd/compact.go", "source_location": "L21", "weight": 1.0, "context": "import"}, {"source": "users_zhijian_golandprojects_juicefs_cmd_compact_go", "target": "go_pkg_path_filepath", "relation": "imports_from", "confidence": "EXTRACTED", "source_file": "cmd/compact.go", "source_location": "L22", "weight": 1.0, "context": "import"}, {"source": "users_zhijian_golandprojects_juicefs_cmd_compact_go", "target": "go_pkg_syscall", "relation": "imports_from", "confidence": "EXTRACTED", "source_file": "cmd/compact.go", "source_location": "L23", "weight": 1.0, "context": "import"}, {"source": "users_zhijian_golandprojects_juicefs_cmd_compact_go", "target": "go_pkg_github_com_juicedata_juicefs_pkg_meta", "relation": "imports_from", "confidence": "EXTRACTED", "source_file": "cmd/compact.go", "source_location": "L25", "weight": 1.0, "context": "import"}, {"source": "users_zhijian_golandprojects_juicefs_cmd_compact_go", "target": "go_pkg_github_com_juicedata_juicefs_pkg_utils", "relation": "imports_from", "confidence": "EXTRACTED", "source_file": "cmd/compact.go", "source_location": "L26", "weight": 1.0, "context": "import"}, {"source": "users_zhijian_golandprojects_juicefs_cmd_compact_go", "target": "go_pkg_github_com_urfave_cli_v2", "relation": "imports_from", "confidence": "EXTRACTED", "source_file": "cmd/compact.go", "source_location": "L27", "weight": 1.0, "context": "import"}, {"source": "users_zhijian_golandprojects_juicefs_cmd_compact_go", "target": "users_zhijian_golandprojects_juicefs_cmd_compact_cmdcompact", "relation": "contains", "confidence": "EXTRACTED", "source_file": "cmd/compact.go", "source_location": "L30", "weight": 1.0}, {"source": "users_zhijian_golandprojects_juicefs_cmd_compact_cmdcompact", "target": "command", "relation": "references", "confidence": "EXTRACTED", "source_file": "cmd/compact.go", "source_location": "L30", "weight": 1.0, "context": "return_type"}, {"source": "users_zhijian_golandprojects_juicefs_cmd_compact_go", "target": "users_zhijian_golandprojects_juicefs_cmd_compact_compact", "relation": "contains", "confidence": "EXTRACTED", "source_file": "cmd/compact.go", "source_location": "L53", "weight": 1.0}, {"source": "users_zhijian_golandprojects_juicefs_cmd_compact_compact", "target": "context", "relation": "references", "confidence": "EXTRACTED", "source_file": "cmd/compact.go", "source_location": "L53", "weight": 1.0, "context": "parameter_type"}, {"source": "users_zhijian_golandprojects_juicefs_cmd_compact_go", "target": "users_zhijian_golandprojects_juicefs_cmd_compact_docompact", "relation": "contains", "confidence": "EXTRACTED", "source_file": "cmd/compact.go", "source_location": "L90", "weight": 1.0}, {"source": "users_zhijian_golandprojects_juicefs_cmd_compact_docompact", "target": "ino", "relation": "references", "confidence": "EXTRACTED", "source_file": "cmd/compact.go", "source_location": "L90", "weight": 1.0, "context": "parameter_type"}, {"source": "users_zhijian_golandprojects_juicefs_cmd_compact_compact", "target": "ino", "relation": "calls", "context": "call", "confidence": "EXTRACTED", "source_file": "cmd/compact.go", "source_location": "L77", "weight": 1.0}, {"source": "users_zhijian_golandprojects_juicefs_cmd_compact_compact", "target": "users_zhijian_golandprojects_juicefs_cmd_compact_docompact", "relation": "calls", "context": "call", "confidence": "EXTRACTED", "source_file": "cmd/compact.go", "source_location": "L83", "weight": 1.0}], "raw_calls": [{"caller_nid": "users_zhijian_golandprojects_juicefs_cmd_compact_compact", "callee": "setup0", "is_member_call": false, "source_file": "cmd/compact.go", "source_location": "L54"}, {"caller_nid": "users_zhijian_golandprojects_juicefs_cmd_compact_compact", "callee": "Int", "is_member_call": true, "source_file": "cmd/compact.go", "source_location": "L56"}, {"caller_nid": "users_zhijian_golandprojects_juicefs_cmd_compact_compact", "callee": "Warn", "is_member_call": true, "source_file": "cmd/compact.go", "source_location": "L58"}, {"caller_nid": "users_zhijian_golandprojects_juicefs_cmd_compact_compact", "callee": "Warn", "is_member_call": true, "source_file": "cmd/compact.go", "source_location": "L61"}, {"caller_nid": "users_zhijian_golandprojects_juicefs_cmd_compact_compact", "callee": "Slice", "is_member_call": true, "source_file": "cmd/compact.go", "source_location": "L65"}, {"caller_nid": "users_zhijian_golandprojects_juicefs_cmd_compact_compact", "callee": "Args", "is_member_call": true, "source_file": "cmd/compact.go", "source_location": "L65"}, {"caller_nid": "users_zhijian_golandprojects_juicefs_cmd_compact_compact", "callee": "Abs", "is_member_call": false, "source_file": "cmd/compact.go", "source_location": "L67"}, {"caller_nid": "users_zhijian_golandprojects_juicefs_cmd_compact_compact", "callee": "Fatalf", "is_member_call": true, "source_file": "cmd/compact.go", "source_location": "L69"}, {"caller_nid": "users_zhijian_golandprojects_juicefs_cmd_compact_compact", "callee": "GetFileInode", "is_member_call": false, "source_file": "cmd/compact.go", "source_location": "L72"}, {"caller_nid": "users_zhijian_golandprojects_juicefs_cmd_compact_compact", "callee": "Errorf", "is_member_call": true, "source_file": "cmd/compact.go", "source_location": "L74"}, {"caller_nid": "users_zhijian_golandprojects_juicefs_cmd_compact_compact", "callee": "IsValid", "is_member_call": true, "source_file": "cmd/compact.go", "source_location": "L79"}, {"caller_nid": "users_zhijian_golandprojects_juicefs_cmd_compact_compact", "callee": "Fatalf", "is_member_call": true, "source_file": "cmd/compact.go", "source_location": "L80"}, {"caller_nid": "users_zhijian_golandprojects_juicefs_cmd_compact_compact", "callee": "uint16", "is_member_call": false, "source_file": "cmd/compact.go", "source_location": "L83"}, {"caller_nid": "users_zhijian_golandprojects_juicefs_cmd_compact_docompact", "callee": "openController", "is_member_call": false, "source_file": "cmd/compact.go", "source_location": "L91"}, {"caller_nid": "users_zhijian_golandprojects_juicefs_cmd_compact_docompact", "callee": "Errorf", "is_member_call": false, "source_file": "cmd/compact.go", "source_location": "L93"}, {"caller_nid": "users_zhijian_golandprojects_juicefs_cmd_compact_docompact", "callee": "Close", "is_member_call": true, "source_file": "cmd/compact.go", "source_location": "L95"}, {"caller_nid": "users_zhijian_golandprojects_juicefs_cmd_compact_docompact", "callee": "uint32", "is_member_call": false, "source_file": "cmd/compact.go", "source_location": "L97"}, {"caller_nid": "users_zhijian_golandprojects_juicefs_cmd_compact_docompact", "callee": "uint32", "is_member_call": false, "source_file": "cmd/compact.go", "source_location": "L97"}, {"caller_nid": "users_zhijian_golandprojects_juicefs_cmd_compact_docompact", "callee": "NewBuffer", "is_member_call": false, "source_file": "cmd/compact.go", "source_location": "L98"}, {"caller_nid": "users_zhijian_golandprojects_juicefs_cmd_compact_docompact", "callee": "Put32", "is_member_call": true, "source_file": "cmd/compact.go", "source_location": "L99"}, {"caller_nid": "users_zhijian_golandprojects_juicefs_cmd_compact_docompact", "callee": "Put32", "is_member_call": true, "source_file": "cmd/compact.go", "source_location": "L100"}, {"caller_nid": "users_zhijian_golandprojects_juicefs_cmd_compact_docompact", "callee": "Put64", "is_member_call": true, "source_file": "cmd/compact.go", "source_location": "L101"}, {"caller_nid": "users_zhijian_golandprojects_juicefs_cmd_compact_docompact", "callee": "uint64", "is_member_call": false, "source_file": "cmd/compact.go", "source_location": "L101"}, {"caller_nid": "users_zhijian_golandprojects_juicefs_cmd_compact_docompact", "callee": "Put16", "is_member_call": true, "source_file": "cmd/compact.go", "source_location": "L102"}, {"caller_nid": "users_zhijian_golandprojects_juicefs_cmd_compact_docompact", "callee": "Write", "is_member_call": true, "source_file": "cmd/compact.go", "source_location": "L104"}, {"caller_nid": "users_zhijian_golandprojects_juicefs_cmd_compact_docompact", "callee": "Bytes", "is_member_call": true, "source_file": "cmd/compact.go", "source_location": "L104"}, {"caller_nid": "users_zhijian_golandprojects_juicefs_cmd_compact_docompact", "callee": "Fatalf", "is_member_call": true, "source_file": "cmd/compact.go", "source_location": "L106"}, {"caller_nid": "users_zhijian_golandprojects_juicefs_cmd_compact_docompact", "callee": "NewProgress", "is_member_call": false, "source_file": "cmd/compact.go", "source_location": "L109"}, {"caller_nid": "users_zhijian_golandprojects_juicefs_cmd_compact_docompact", "callee": "AddCountBar", "is_member_call": true, "source_file": "cmd/compact.go", "source_location": "L110"}, {"caller_nid": "users_zhijian_golandprojects_juicefs_cmd_compact_docompact", "callee": "readProgress", "is_member_call": false, "source_file": "cmd/compact.go", "source_location": "L111"}, {"caller_nid": "users_zhijian_golandprojects_juicefs_cmd_compact_docompact", "callee": "SetTotal", "is_member_call": true, "source_file": "cmd/compact.go", "source_location": "L112"}, {"caller_nid": "users_zhijian_golandprojects_juicefs_cmd_compact_docompact", "callee": "int64", "is_member_call": false, "source_file": "cmd/compact.go", "source_location": "L112"}, {"caller_nid": "users_zhijian_golandprojects_juicefs_cmd_compact_docompact", "callee": "SetCurrent", "is_member_call": true, "source_file": "cmd/compact.go", "source_location": "L113"}, {"caller_nid": "users_zhijian_golandprojects_juicefs_cmd_compact_docompact", "callee": "int64", "is_member_call": false, "source_file": "cmd/compact.go", "source_location": "L113"}, {"caller_nid": "users_zhijian_golandprojects_juicefs_cmd_compact_docompact", "callee": "Done", "is_member_call": true, "source_file": "cmd/compact.go", "source_location": "L116"}, {"caller_nid": "users_zhijian_golandprojects_juicefs_cmd_compact_docompact", "callee": "Done", "is_member_call": true, "source_file": "cmd/compact.go", "source_location": "L117"}, {"caller_nid": "users_zhijian_golandprojects_juicefs_cmd_compact_docompact", "callee": "Fatalf", "is_member_call": true, "source_file": "cmd/compact.go", "source_location": "L120"}, {"caller_nid": "users_zhijian_golandprojects_juicefs_cmd_compact_docompact", "callee": "Errorf", "is_member_call": false, "source_file": "cmd/compact.go", "source_location": "L123"}, {"caller_nid": "users_zhijian_golandprojects_juicefs_cmd_compact_docompact", "callee": "Infof", "is_member_call": true, "source_file": "cmd/compact.go", "source_location": "L126"}]}