{"nodes": [{"id": "users_zhijian_golandprojects_juicefs_pkg_sync_checkpoint_go", "label": "checkpoint.go", "file_type": "code", "source_file": "pkg/sync/checkpoint.go", "source_location": "L1"}, {"id": "sync_prefixstate", "label": "PrefixState", "file_type": "code", "source_file": "pkg/sync/checkpoint.go", "source_location": "L44"}, {"id": "rwmutex", "label": "RWMutex", "file_type": "code", "source_file": "", "source_location": "", "origin_file": "/Users/zhijian/GolandProjects/juicefs/pkg/sync/checkpoint.go"}, {"id": "object", "label": "Object", "file_type": "code", "source_file": "", "source_location": "", "origin_file": "/Users/zhijian/GolandProjects/juicefs/pkg/sync/checkpoint.go"}, {"id": "sync_prefixstatejson", "label": "prefixStateJSON", "file_type": "code", "source_file": "pkg/sync/checkpoint.go", "source_location": "L54"}, {"id": "sync_prefixstate_marshaljson", "label": ".MarshalJSON()", "file_type": "code", "source_file": "pkg/sync/checkpoint.go", "source_location": "L62"}, {"id": "sync_prefixstate_unmarshaljson", "label": ".UnmarshalJSON()", "file_type": "code", "source_file": "pkg/sync/checkpoint.go", "source_location": "L79"}, {"id": "sync_checkpointstats", "label": "CheckpointStats", "file_type": "code", "source_file": "pkg/sync/checkpoint.go", "source_location": "L103"}, {"id": "sync_multipartuploadstate", "label": "multipartUploadState", "file_type": "code", "source_file": "pkg/sync/checkpoint.go", "source_location": "L115"}, {"id": "multipartupload", "label": "MultipartUpload", "file_type": "code", "source_file": "", "source_location": "", "origin_file": "/Users/zhijian/GolandProjects/juicefs/pkg/sync/checkpoint.go"}, {"id": "time", "label": "Time", "file_type": "code", "source_file": "", "source_location": "", "origin_file": "/Users/zhijian/GolandProjects/juicefs/pkg/sync/checkpoint.go"}, {"id": "part", "label": "Part", "file_type": "code", "source_file": "", "source_location": "", "origin_file": "/Users/zhijian/GolandProjects/juicefs/pkg/sync/checkpoint.go"}, {"id": "sync_multipartuploads", "label": "multipartUploads", "file_type": "code", "source_file": "pkg/sync/checkpoint.go", "source_location": "L123"}, {"id": "sync_checkpoint", "label": "Checkpoint", "file_type": "code", "source_file": "pkg/sync/checkpoint.go", "source_location": "L133"}, {"id": "config", "label": "Config", "file_type": "code", "source_file": "", "source_location": "", "origin_file": "/Users/zhijian/GolandProjects/juicefs/pkg/sync/checkpoint.go"}, {"id": "sync_checkpointmanager", "label": "CheckpointManager", "file_type": "code", "source_file": "pkg/sync/checkpoint.go", "source_location": "L145"}, {"id": "mutex", "label": "Mutex", "file_type": "code", "source_file": "", "source_location": "", "origin_file": "/Users/zhijian/GolandProjects/juicefs/pkg/sync/checkpoint.go"}, {"id": "multipartuploadstore", "label": "multipartUploadStore", "file_type": "code", "source_file": "", "source_location": "", "origin_file": "/Users/zhijian/GolandProjects/juicefs/pkg/sync/checkpoint.go"}, {"id": "objectstorage", "label": "ObjectStorage", "file_type": "code", "source_file": "", "source_location": "", "origin_file": "/Users/zhijian/GolandProjects/juicefs/pkg/sync/checkpoint.go"}, {"id": "once", "label": "Once", "file_type": "code", "source_file": "", "source_location": "", "origin_file": "/Users/zhijian/GolandProjects/juicefs/pkg/sync/checkpoint.go"}, {"id": "map", "label": "Map", "file_type": "code", "source_file": "", "source_location": "", "origin_file": "/Users/zhijian/GolandProjects/juicefs/pkg/sync/checkpoint.go"}, {"id": "users_zhijian_golandprojects_juicefs_pkg_sync_checkpoint_newcheckpoint", "label": "newCheckpoint()", "file_type": "code", "source_file": "pkg/sync/checkpoint.go", "source_location": "L159"}, {"id": "users_zhijian_golandprojects_juicefs_pkg_sync_checkpoint_newcheckpointmanager", "label": "NewCheckpointManager()", "file_type": "code", "source_file": "pkg/sync/checkpoint.go", "source_location": "L169"}, {"id": "users_zhijian_golandprojects_juicefs_pkg_sync_checkpoint_generatecheckpointkey", "label": "generateCheckpointKey()", "file_type": "code", "source_file": "pkg/sync/checkpoint.go", "source_location": "L183"}, {"id": "sync_checkpointmanager_ischeckpointkey", "label": ".isCheckpointKey()", "file_type": "code", "source_file": "pkg/sync/checkpoint.go", "source_location": "L202"}, {"id": "users_zhijian_golandprojects_juicefs_pkg_sync_checkpoint_checkpointtmpprefix", "label": "checkpointTmpPrefix()", "file_type": "code", "source_file": "pkg/sync/checkpoint.go", "source_location": "L206"}, {"id": "sync_checkpointmanager_cleanupcheckpointtmp", "label": ".cleanupCheckpointTmp()", "file_type": "code", "source_file": "pkg/sync/checkpoint.go", "source_location": "L219"}, {"id": "sync_checkpointmanager_load", "label": ".Load()", "file_type": "code", "source_file": "pkg/sync/checkpoint.go", "source_location": "L238"}, {"id": "sync_checkpointmanager_save", "label": ".Save()", "file_type": "code", "source_file": "pkg/sync/checkpoint.go", "source_location": "L269"}, {"id": "sync_checkpointmanager_validateconfig", "label": ".ValidateConfig()", "file_type": "code", "source_file": "pkg/sync/checkpoint.go", "source_location": "L315"}, {"id": "sync_checkpointmanager_getorcreateprefixstate", "label": ".GetOrCreatePrefixState()", "file_type": "code", "source_file": "pkg/sync/checkpoint.go", "source_location": "L376"}, {"id": "sync_checkpointmanager_updateprefixstate", "label": ".updatePrefixState()", "file_type": "code", "source_file": "pkg/sync/checkpoint.go", "source_location": "L398"}, {"id": "sync_checkpointmanager_marklistdone", "label": ".MarkListDone()", "file_type": "code", "source_file": "pkg/sync/checkpoint.go", "source_location": "L413"}, {"id": "sync_multipartuploadstore", "label": "multipartUploadStore", "file_type": "code", "source_file": "pkg/sync/checkpoint.go", "source_location": "L422"}, {"id": "users_zhijian_golandprojects_juicefs_pkg_sync_checkpoint_newmultipartuploadstore", "label": "newMultipartUploadStore()", "file_type": "code", "source_file": "pkg/sync/checkpoint.go", "source_location": "L427"}, {"id": "sync_multipartuploadstate_isvalid", "label": ".isValid()", "file_type": "code", "source_file": "pkg/sync/checkpoint.go", "source_location": "L434"}, {"id": "sync_multipartuploadstate_ismatched", "label": ".isMatched()", "file_type": "code", "source_file": "pkg/sync/checkpoint.go", "source_location": "L439"}, {"id": "sync_multipartuploadstore_reset", "label": ".reset()", "file_type": "code", "source_file": "pkg/sync/checkpoint.go", "source_location": "L443"}, {"id": "sync_multipartuploadstore_findmultipartupload", "label": ".FindMultipartUpload()", "file_type": "code", "source_file": "pkg/sync/checkpoint.go", "source_location": "L452"}, {"id": "sync_multipartuploadstore_getmultipartcheckpoint", "label": ".GetMultipartCheckpoint()", "file_type": "code", "source_file": "pkg/sync/checkpoint.go", "source_location": "L461"}, {"id": "sync_multipartuploadstore_putmultipartcheckpoint", "label": ".PutMultipartCheckpoint()", "file_type": "code", "source_file": "pkg/sync/checkpoint.go", "source_location": "L470"}, {"id": "sync_multipartuploadstore_ensuremultipartuploadstate", "label": ".EnsureMultipartUploadState()", "file_type": "code", "source_file": "pkg/sync/checkpoint.go", "source_location": "L496"}, {"id": "sync_multipartuploadstore_markmultipartpart", "label": ".MarkMultipartPart()", "file_type": "code", "source_file": "pkg/sync/checkpoint.go", "source_location": "L518"}, {"id": "sync_multipartuploadstore_getmultipartpart", "label": ".GetMultipartPart()", "file_type": "code", "source_file": "pkg/sync/checkpoint.go", "source_location": "L537"}, {"id": "sync_multipartuploadstore_finishmultipartupload", "label": ".FinishMultipartUpload()", "file_type": "code", "source_file": "pkg/sync/checkpoint.go", "source_location": "L557"}, {"id": "sync_workermultipartuploads", "label": "workerMultipartUploads", "file_type": "code", "source_file": "pkg/sync/checkpoint.go", "source_location": "L563"}, {"id": "users_zhijian_golandprojects_juicefs_pkg_sync_checkpoint_newworkermultipartuploads", "label": "newWorkerMultipartUploads()", "file_type": "code", "source_file": "pkg/sync/checkpoint.go", "source_location": "L568"}, {"id": "sync_workermultipartuploads_markmultipartpart", "label": ".MarkMultipartPart()", "file_type": "code", "source_file": "pkg/sync/checkpoint.go", "source_location": "L575"}, {"id": "sync_workermultipartuploads_finishmultipartupload", "label": ".FinishMultipartUpload()", "file_type": "code", "source_file": "pkg/sync/checkpoint.go", "source_location": "L601"}, {"id": "sync_checkpointmanager_markcompleted", "label": ".MarkCompleted()", "file_type": "code", "source_file": "pkg/sync/checkpoint.go", "source_location": "L609"}, {"id": "sync_checkpointmanager_markfailed", "label": ".MarkFailed()", "file_type": "code", "source_file": "pkg/sync/checkpoint.go", "source_location": "L628"}, {"id": "sync_checkpointmanager_addpendingkey", "label": ".AddPendingKey()", "file_type": "code", "source_file": "pkg/sync/checkpoint.go", "source_location": "L648"}, {"id": "sync_checkpointmanager_updatelastlistedkey", "label": ".UpdateLastListedKey()", "file_type": "code", "source_file": "pkg/sync/checkpoint.go", "source_location": "L659"}, {"id": "sync_checkpointmanager_trackkey", "label": ".TrackKey()", "file_type": "code", "source_file": "pkg/sync/checkpoint.go", "source_location": "L668"}, {"id": "sync_checkpointmanager_getlastlistedkey", "label": ".GetLastListedKey()", "file_type": "code", "source_file": "pkg/sync/checkpoint.go", "source_location": "L676"}, {"id": "sync_checkpointmanager_restoreprefix", "label": ".RestorePrefix()", "file_type": "code", "source_file": "pkg/sync/checkpoint.go", "source_location": "L692"}, {"id": "sync_checkpointmanager_listprefixes", "label": ".ListPrefixes()", "file_type": "code", "source_file": "pkg/sync/checkpoint.go", "source_location": "L723"}, {"id": "sync_checkpointmanager_registerchildprefix", "label": ".RegisterChildPrefix()", "file_type": "code", "source_file": "pkg/sync/checkpoint.go", "source_location": "L737"}, {"id": "sync_checkpointmanager_stop", "label": ".Stop()", "file_type": "code", "source_file": "pkg/sync/checkpoint.go", "source_location": "L747"}, {"id": "sync_checkpointmanager_deletecheckpoint", "label": ".DeleteCheckpoint()", "file_type": "code", "source_file": "pkg/sync/checkpoint.go", "source_location": "L757"}, {"id": "sync_checkpointmanager_reset", "label": ".Reset()", "file_type": "code", "source_file": "pkg/sync/checkpoint.go", "source_location": "L764"}, {"id": "sync_checkpointmanager_startperiodicsave", "label": ".StartPeriodicSave()", "file_type": "code", "source_file": "pkg/sync/checkpoint.go", "source_location": "L770"}, {"id": "duration", "label": "Duration", "file_type": "code", "source_file": "", "source_location": "", "origin_file": "/Users/zhijian/GolandProjects/juicefs/pkg/sync/checkpoint.go"}, {"id": "sync_checkpointmanager_saveonsignal", "label": ".SaveOnSignal()", "file_type": "code", "source_file": "pkg/sync/checkpoint.go", "source_location": "L793"}, {"id": "users_zhijian_golandprojects_juicefs_pkg_sync_checkpoint_trackcheckpointcompletion", "label": "trackCheckpointCompletion()", "file_type": "code", "source_file": "pkg/sync/checkpoint.go", "source_location": "L813"}], "edges": [{"source": "users_zhijian_golandprojects_juicefs_pkg_sync_checkpoint_go", "target": "go_pkg_bytes", "relation": "imports_from", "confidence": "EXTRACTED", "source_file": "pkg/sync/checkpoint.go", "source_location": "L20", "weight": 1.0, "context": "import"}, {"source": "users_zhijian_golandprojects_juicefs_pkg_sync_checkpoint_go", "target": "go_pkg_crypto_md5", "relation": "imports_from", "confidence": "EXTRACTED", "source_file": "pkg/sync/checkpoint.go", "source_location": "L21", "weight": 1.0, "context": "import"}, {"source": "users_zhijian_golandprojects_juicefs_pkg_sync_checkpoint_go", "target": "go_pkg_encoding_json", "relation": "imports_from", "confidence": "EXTRACTED", "source_file": "pkg/sync/checkpoint.go", "source_location": "L22", "weight": 1.0, "context": "import"}, {"source": "users_zhijian_golandprojects_juicefs_pkg_sync_checkpoint_go", "target": "go_pkg_errors", "relation": "imports_from", "confidence": "EXTRACTED", "source_file": "pkg/sync/checkpoint.go", "source_location": "L23", "weight": 1.0, "context": "import"}, {"source": "users_zhijian_golandprojects_juicefs_pkg_sync_checkpoint_go", "target": "go_pkg_fmt", "relation": "imports_from", "confidence": "EXTRACTED", "source_file": "pkg/sync/checkpoint.go", "source_location": "L24", "weight": 1.0, "context": "import"}, {"source": "users_zhijian_golandprojects_juicefs_pkg_sync_checkpoint_go", "target": "go_pkg_io", "relation": "imports_from", "confidence": "EXTRACTED", "source_file": "pkg/sync/checkpoint.go", "source_location": "L25", "weight": 1.0, "context": "import"}, {"source": "users_zhijian_golandprojects_juicefs_pkg_sync_checkpoint_go", "target": "go_pkg_maps", "relation": "imports_from", "confidence": "EXTRACTED", "source_file": "pkg/sync/checkpoint.go", "source_location": "L26", "weight": 1.0, "context": "import"}, {"source": "users_zhijian_golandprojects_juicefs_pkg_sync_checkpoint_go", "target": "go_pkg_os", "relation": "imports_from", "confidence": "EXTRACTED", "source_file": "pkg/sync/checkpoint.go", "source_location": "L27", "weight": 1.0, "context": "import"}, {"source": "users_zhijian_golandprojects_juicefs_pkg_sync_checkpoint_go", "target": "go_pkg_os_signal", "relation": "imports_from", "confidence": "EXTRACTED", "source_file": "pkg/sync/checkpoint.go", "source_location": "L28", "weight": 1.0, "context": "import"}, {"source": "users_zhijian_golandprojects_juicefs_pkg_sync_checkpoint_go", "target": "go_pkg_path", "relation": "imports_from", "confidence": "EXTRACTED", "source_file": "pkg/sync/checkpoint.go", "source_location": "L29", "weight": 1.0, "context": "import"}, {"source": "users_zhijian_golandprojects_juicefs_pkg_sync_checkpoint_go", "target": "go_pkg_slices", "relation": "imports_from", "confidence": "EXTRACTED", "source_file": "pkg/sync/checkpoint.go", "source_location": "L30", "weight": 1.0, "context": "import"}, {"source": "users_zhijian_golandprojects_juicefs_pkg_sync_checkpoint_go", "target": "go_pkg_strings", "relation": "imports_from", "confidence": "EXTRACTED", "source_file": "pkg/sync/checkpoint.go", "source_location": "L31", "weight": 1.0, "context": "import"}, {"source": "users_zhijian_golandprojects_juicefs_pkg_sync_checkpoint_go", "target": "go_pkg_sync", "relation": "imports_from", "confidence": "EXTRACTED", "source_file": "pkg/sync/checkpoint.go", "source_location": "L32", "weight": 1.0, "context": "import"}, {"source": "users_zhijian_golandprojects_juicefs_pkg_sync_checkpoint_go", "target": "go_pkg_syscall", "relation": "imports_from", "confidence": "EXTRACTED", "source_file": "pkg/sync/checkpoint.go", "source_location": "L33", "weight": 1.0, "context": "import"}, {"source": "users_zhijian_golandprojects_juicefs_pkg_sync_checkpoint_go", "target": "go_pkg_time", "relation": "imports_from", "confidence": "EXTRACTED", "source_file": "pkg/sync/checkpoint.go", "source_location": "L34", "weight": 1.0, "context": "import"}, {"source": "users_zhijian_golandprojects_juicefs_pkg_sync_checkpoint_go", "target": "go_pkg_github_com_juicedata_juicefs_pkg_object", "relation": "imports_from", "confidence": "EXTRACTED", "source_file": "pkg/sync/checkpoint.go", "source_location": "L36", "weight": 1.0, "context": "import"}, {"source": "users_zhijian_golandprojects_juicefs_pkg_sync_checkpoint_go", "target": "sync_prefixstate", "relation": "contains", "confidence": "EXTRACTED", "source_file": "pkg/sync/checkpoint.go", "source_location": "L44", "weight": 1.0}, {"source": "sync_prefixstate", "target": "rwmutex", "relation": "embeds", "confidence": "EXTRACTED", "source_file": "pkg/sync/checkpoint.go", "source_location": "L45", "weight": 1.0}, {"source": "sync_prefixstate", "target": "object", "relation": "references", "confidence": "EXTRACTED", "source_file": "pkg/sync/checkpoint.go", "source_location": "L49", "weight": 1.0, "context": "field"}, {"source": "sync_prefixstate", "target": "object", "relation": "references", "confidence": "EXTRACTED", "source_file": "pkg/sync/checkpoint.go", "source_location": "L50", "weight": 1.0, "context": "field"}, {"source": "users_zhijian_golandprojects_juicefs_pkg_sync_checkpoint_go", "target": "sync_prefixstatejson", "relation": "contains", "confidence": "EXTRACTED", "source_file": "pkg/sync/checkpoint.go", "source_location": "L54", "weight": 1.0}, {"source": "sync_prefixstate", "target": "sync_prefixstate_marshaljson", "relation": "method", "confidence": "EXTRACTED", "source_file": "pkg/sync/checkpoint.go", "source_location": "L62", "weight": 1.0}, {"source": "sync_prefixstate", "target": "sync_prefixstate_unmarshaljson", "relation": "method", "confidence": "EXTRACTED", "source_file": "pkg/sync/checkpoint.go", "source_location": "L79", "weight": 1.0}, {"source": "users_zhijian_golandprojects_juicefs_pkg_sync_checkpoint_go", "target": "sync_checkpointstats", "relation": "contains", "confidence": "EXTRACTED", "source_file": "pkg/sync/checkpoint.go", "source_location": "L103", "weight": 1.0}, {"source": "users_zhijian_golandprojects_juicefs_pkg_sync_checkpoint_go", "target": "sync_multipartuploadstate", "relation": "contains", "confidence": "EXTRACTED", "source_file": "pkg/sync/checkpoint.go", "source_location": "L115", "weight": 1.0}, {"source": "sync_multipartuploadstate", "target": "multipartupload", "relation": "references", "confidence": "EXTRACTED", "source_file": "pkg/sync/checkpoint.go", "source_location": "L116", "weight": 1.0, "context": "field"}, {"source": "sync_multipartuploadstate", "target": "time", "relation": "references", "confidence": "EXTRACTED", "source_file": "pkg/sync/checkpoint.go", "source_location": "L118", "weight": 1.0, "context": "field"}, {"source": "sync_multipartuploadstate", "target": "part", "relation": "references", "confidence": "EXTRACTED", "source_file": "pkg/sync/checkpoint.go", "source_location": "L119", "weight": 1.0, "context": "field"}, {"source": "users_zhijian_golandprojects_juicefs_pkg_sync_checkpoint_go", "target": "sync_multipartuploads", "relation": "contains", "confidence": "EXTRACTED", "source_file": "pkg/sync/checkpoint.go", "source_location": "L123", "weight": 1.0}, {"source": "users_zhijian_golandprojects_juicefs_pkg_sync_checkpoint_go", "target": "sync_checkpoint", "relation": "contains", "confidence": "EXTRACTED", "source_file": "pkg/sync/checkpoint.go", "source_location": "L133", "weight": 1.0}, {"source": "sync_checkpoint", "target": "rwmutex", "relation": "embeds", "confidence": "EXTRACTED", "source_file": "pkg/sync/checkpoint.go", "source_location": "L134", "weight": 1.0}, {"source": "sync_checkpoint", "target": "sync_prefixstate", "relation": "references", "confidence": "EXTRACTED", "source_file": "pkg/sync/checkpoint.go", "source_location": "L135", "weight": 1.0, "context": "field"}, {"source": "sync_checkpoint", "target": "sync_multipartuploadstate", "relation": "references", "confidence": "EXTRACTED", "source_file": "pkg/sync/checkpoint.go", "source_location": "L136", "weight": 1.0, "context": "field"}, {"source": "sync_checkpoint", "target": "config", "relation": "references", "confidence": "EXTRACTED", "source_file": "pkg/sync/checkpoint.go", "source_location": "L137", "weight": 1.0, "context": "field"}, {"source": "sync_checkpoint", "target": "sync_checkpointstats", "relation": "references", "confidence": "EXTRACTED", "source_file": "pkg/sync/checkpoint.go", "source_location": "L138", "weight": 1.0, "context": "field"}, {"source": "sync_checkpoint", "target": "time", "relation": "references", "confidence": "EXTRACTED", "source_file": "pkg/sync/checkpoint.go", "source_location": "L141", "weight": 1.0, "context": "field"}, {"source": "users_zhijian_golandprojects_juicefs_pkg_sync_checkpoint_go", "target": "sync_checkpointmanager", "relation": "contains", "confidence": "EXTRACTED", "source_file": "pkg/sync/checkpoint.go", "source_location": "L145", "weight": 1.0}, {"source": "sync_checkpointmanager", "target": "mutex", "relation": "references", "confidence": "EXTRACTED", "source_file": "pkg/sync/checkpoint.go", "source_location": "L146", "weight": 1.0, "context": "field"}, {"source": "sync_checkpointmanager", "target": "multipartuploadstore", "relation": "embeds", "confidence": "EXTRACTED", "source_file": "pkg/sync/checkpoint.go", "source_location": "L147", "weight": 1.0}, {"source": "sync_checkpointmanager", "target": "objectstorage", "relation": "references", "confidence": "EXTRACTED", "source_file": "pkg/sync/checkpoint.go", "source_location": "L148", "weight": 1.0, "context": "field"}, {"source": "sync_checkpointmanager", "target": "sync_checkpoint", "relation": "references", "confidence": "EXTRACTED", "source_file": "pkg/sync/checkpoint.go", "source_location": "L149", "weight": 1.0, "context": "field"}, {"source": "sync_checkpointmanager", "target": "once", "relation": "references", "confidence": "EXTRACTED", "source_file": "pkg/sync/checkpoint.go", "source_location": "L152", "weight": 1.0, "context": "field"}, {"source": "sync_checkpointmanager", "target": "map", "relation": "references", "confidence": "EXTRACTED", "source_file": "pkg/sync/checkpoint.go", "source_location": "L154", "weight": 1.0, "context": "field"}, {"source": "sync_checkpointmanager", "target": "sync_checkpointstats", "relation": "references", "confidence": "EXTRACTED", "source_file": "pkg/sync/checkpoint.go", "source_location": "L155", "weight": 1.0, "context": "field"}, {"source": "sync_checkpointmanager", "target": "map", "relation": "references", "confidence": "EXTRACTED", "source_file": "pkg/sync/checkpoint.go", "source_location": "L156", "weight": 1.0, "context": "field"}, {"source": "users_zhijian_golandprojects_juicefs_pkg_sync_checkpoint_go", "target": "users_zhijian_golandprojects_juicefs_pkg_sync_checkpoint_newcheckpoint", "relation": "contains", "confidence": "EXTRACTED", "source_file": "pkg/sync/checkpoint.go", "source_location": "L159", "weight": 1.0}, {"source": "users_zhijian_golandprojects_juicefs_pkg_sync_checkpoint_newcheckpoint", "target": "config", "relation": "references", "confidence": "EXTRACTED", "source_file": "pkg/sync/checkpoint.go", "source_location": "L159", "weight": 1.0, "context": "parameter_type"}, {"source": "users_zhijian_golandprojects_juicefs_pkg_sync_checkpoint_newcheckpoint", "target": "sync_checkpoint", "relation": "references", "confidence": "EXTRACTED", "source_file": "pkg/sync/checkpoint.go", "source_location": "L159", "weight": 1.0, "context": "return_type"}, {"source": "users_zhijian_golandprojects_juicefs_pkg_sync_checkpoint_go", "target": "users_zhijian_golandprojects_juicefs_pkg_sync_checkpoint_newcheckpointmanager", "relation": "contains", "confidence": "EXTRACTED", "source_file": "pkg/sync/checkpoint.go", "source_location": "L169", "weight": 1.0}, {"source": "users_zhijian_golandprojects_juicefs_pkg_sync_checkpoint_newcheckpointmanager", "target": "objectstorage", "relation": "references", "confidence": "EXTRACTED", "source_file": "pkg/sync/checkpoint.go", "source_location": "L169", "weight": 1.0, "context": "parameter_type"}, {"source": "users_zhijian_golandprojects_juicefs_pkg_sync_checkpoint_newcheckpointmanager", "target": "config", "relation": "references", "confidence": "EXTRACTED", "source_file": "pkg/sync/checkpoint.go", "source_location": "L169", "weight": 1.0, "context": "parameter_type"}, {"source": "users_zhijian_golandprojects_juicefs_pkg_sync_checkpoint_newcheckpointmanager", "target": "sync_checkpointmanager", "relation": "references", "confidence": "EXTRACTED", "source_file": "pkg/sync/checkpoint.go", "source_location": "L169", "weight": 1.0, "context": "return_type"}, {"source": "users_zhijian_golandprojects_juicefs_pkg_sync_checkpoint_go", "target": "users_zhijian_golandprojects_juicefs_pkg_sync_checkpoint_generatecheckpointkey", "relation": "contains", "confidence": "EXTRACTED", "source_file": "pkg/sync/checkpoint.go", "source_location": "L183", "weight": 1.0}, {"source": "users_zhijian_golandprojects_juicefs_pkg_sync_checkpoint_generatecheckpointkey", "target": "config", "relation": "references", "confidence": "EXTRACTED", "source_file": "pkg/sync/checkpoint.go", "source_location": "L183", "weight": 1.0, "context": "parameter_type"}, {"source": "sync_checkpointmanager", "target": "sync_checkpointmanager_ischeckpointkey", "relation": "method", "confidence": "EXTRACTED", "source_file": "pkg/sync/checkpoint.go", "source_location": "L202", "weight": 1.0}, {"source": "users_zhijian_golandprojects_juicefs_pkg_sync_checkpoint_go", "target": "users_zhijian_golandprojects_juicefs_pkg_sync_checkpoint_checkpointtmpprefix", "relation": "contains", "confidence": "EXTRACTED", "source_file": "pkg/sync/checkpoint.go", "source_location": "L206", "weight": 1.0}, {"source": "sync_checkpointmanager", "target": "sync_checkpointmanager_cleanupcheckpointtmp", "relation": "method", "confidence": "EXTRACTED", "source_file": "pkg/sync/checkpoint.go", "source_location": "L219", "weight": 1.0}, {"source": "sync_checkpointmanager", "target": "sync_checkpointmanager_load", "relation": "method", "confidence": "EXTRACTED", "source_file": "pkg/sync/checkpoint.go", "source_location": "L238", "weight": 1.0}, {"source": "sync_checkpointmanager_load", "target": "sync_checkpoint", "relation": "references", "confidence": "EXTRACTED", "source_file": "pkg/sync/checkpoint.go", "source_location": "L238", "weight": 1.0, "context": "return_type"}, {"source": "sync_checkpointmanager", "target": "sync_checkpointmanager_save", "relation": "method", "confidence": "EXTRACTED", "source_file": "pkg/sync/checkpoint.go", "source_location": "L269", "weight": 1.0}, {"source": "sync_checkpointmanager_save", "target": "sync_checkpoint", "relation": "references", "confidence": "EXTRACTED", "source_file": "pkg/sync/checkpoint.go", "source_location": "L269", "weight": 1.0, "context": "parameter_type"}, {"source": "sync_checkpointmanager", "target": "sync_checkpointmanager_validateconfig", "relation": "method", "confidence": "EXTRACTED", "source_file": "pkg/sync/checkpoint.go", "source_location": "L315", "weight": 1.0}, {"source": "sync_checkpointmanager_validateconfig", "target": "config", "relation": "references", "confidence": "EXTRACTED", "source_file": "pkg/sync/checkpoint.go", "source_location": "L315", "weight": 1.0, "context": "parameter_type"}, {"source": "sync_checkpointmanager", "target": "sync_checkpointmanager_getorcreateprefixstate", "relation": "method", "confidence": "EXTRACTED", "source_file": "pkg/sync/checkpoint.go", "source_location": "L376", "weight": 1.0}, {"source": "sync_checkpointmanager_getorcreateprefixstate", "target": "sync_prefixstate", "relation": "references", "confidence": "EXTRACTED", "source_file": "pkg/sync/checkpoint.go", "source_location": "L376", "weight": 1.0, "context": "return_type"}, {"source": "sync_checkpointmanager", "target": "sync_checkpointmanager_updateprefixstate", "relation": "method", "confidence": "EXTRACTED", "source_file": "pkg/sync/checkpoint.go", "source_location": "L398", "weight": 1.0}, {"source": "sync_checkpointmanager_updateprefixstate", "target": "sync_prefixstate", "relation": "references", "confidence": "EXTRACTED", "source_file": "pkg/sync/checkpoint.go", "source_location": "L398", "weight": 1.0, "context": "parameter_type"}, {"source": "sync_checkpointmanager", "target": "sync_checkpointmanager_marklistdone", "relation": "method", "confidence": "EXTRACTED", "source_file": "pkg/sync/checkpoint.go", "source_location": "L413", "weight": 1.0}, {"source": "users_zhijian_golandprojects_juicefs_pkg_sync_checkpoint_go", "target": "sync_multipartuploadstore", "relation": "contains", "confidence": "EXTRACTED", "source_file": "pkg/sync/checkpoint.go", "source_location": "L422", "weight": 1.0}, {"source": "sync_multipartuploadstore", "target": "rwmutex", "relation": "embeds", "confidence": "EXTRACTED", "source_file": "pkg/sync/checkpoint.go", "source_location": "L423", "weight": 1.0}, {"source": "sync_multipartuploadstore", "target": "sync_multipartuploadstate", "relation": "references", "confidence": "EXTRACTED", "source_file": "pkg/sync/checkpoint.go", "source_location": "L424", "weight": 1.0, "context": "field"}, {"source": "users_zhijian_golandprojects_juicefs_pkg_sync_checkpoint_go", "target": "users_zhijian_golandprojects_juicefs_pkg_sync_checkpoint_newmultipartuploadstore", "relation": "contains", "confidence": "EXTRACTED", "source_file": "pkg/sync/checkpoint.go", "source_location": "L427", "weight": 1.0}, {"source": "users_zhijian_golandprojects_juicefs_pkg_sync_checkpoint_newmultipartuploadstore", "target": "sync_multipartuploadstate", "relation": "references", "confidence": "EXTRACTED", "source_file": "pkg/sync/checkpoint.go", "source_location": "L427", "weight": 1.0, "context": "parameter_type"}, {"source": "users_zhijian_golandprojects_juicefs_pkg_sync_checkpoint_newmultipartuploadstore", "target": "sync_multipartuploadstore", "relation": "references", "confidence": "EXTRACTED", "source_file": "pkg/sync/checkpoint.go", "source_location": "L427", "weight": 1.0, "context": "return_type"}, {"source": "sync_multipartuploadstate", "target": "sync_multipartuploadstate_isvalid", "relation": "method", "confidence": "EXTRACTED", "source_file": "pkg/sync/checkpoint.go", "source_location": "L434", "weight": 1.0}, {"source": "sync_multipartuploadstate", "target": "sync_multipartuploadstate_ismatched", "relation": "method", "confidence": "EXTRACTED", "source_file": "pkg/sync/checkpoint.go", "source_location": "L439", "weight": 1.0}, {"source": "sync_multipartuploadstate_ismatched", "target": "time", "relation": "references", "confidence": "EXTRACTED", "source_file": "pkg/sync/checkpoint.go", "source_location": "L439", "weight": 1.0, "context": "parameter_type"}, {"source": "sync_multipartuploadstore", "target": "sync_multipartuploadstore_reset", "relation": "method", "confidence": "EXTRACTED", "source_file": "pkg/sync/checkpoint.go", "source_location": "L443", "weight": 1.0}, {"source": "sync_multipartuploadstore_reset", "target": "sync_multipartuploadstate", "relation": "references", "confidence": "EXTRACTED", "source_file": "pkg/sync/checkpoint.go", "source_location": "L443", "weight": 1.0, "context": "parameter_type"}, {"source": "sync_multipartuploadstore", "target": "sync_multipartuploadstore_findmultipartupload", "relation": "method", "confidence": "EXTRACTED", "source_file": "pkg/sync/checkpoint.go", "source_location": "L452", "weight": 1.0}, {"source": "sync_multipartuploadstore_findmultipartupload", "target": "time", "relation": "references", "confidence": "EXTRACTED", "source_file": "pkg/sync/checkpoint.go", "source_location": "L452", "weight": 1.0, "context": "parameter_type"}, {"source": "sync_multipartuploadstore_findmultipartupload", "target": "multipartupload", "relation": "references", "confidence": "EXTRACTED", "source_file": "pkg/sync/checkpoint.go", "source_location": "L452", "weight": 1.0, "context": "return_type"}, {"source": "sync_multipartuploadstore", "target": "sync_multipartuploadstore_getmultipartcheckpoint", "relation": "method", "confidence": "EXTRACTED", "source_file": "pkg/sync/checkpoint.go", "source_location": "L461", "weight": 1.0}, {"source": "sync_multipartuploadstore_getmultipartcheckpoint", "target": "time", "relation": "references", "confidence": "EXTRACTED", "source_file": "pkg/sync/checkpoint.go", "source_location": "L461", "weight": 1.0, "context": "parameter_type"}, {"source": "sync_multipartuploadstore_getmultipartcheckpoint", "target": "sync_multipartuploadstate", "relation": "references", "confidence": "EXTRACTED", "source_file": "pkg/sync/checkpoint.go", "source_location": "L461", "weight": 1.0, "context": "return_type"}, {"source": "sync_multipartuploadstore", "target": "sync_multipartuploadstore_putmultipartcheckpoint", "relation": "method", "confidence": "EXTRACTED", "source_file": "pkg/sync/checkpoint.go", "source_location": "L470", "weight": 1.0}, {"source": "sync_multipartuploadstore_putmultipartcheckpoint", "target": "sync_multipartuploadstate", "relation": "references", "confidence": "EXTRACTED", "source_file": "pkg/sync/checkpoint.go", "source_location": "L470", "weight": 1.0, "context": "parameter_type"}, {"source": "sync_multipartuploadstore", "target": "sync_multipartuploadstore_ensuremultipartuploadstate", "relation": "method", "confidence": "EXTRACTED", "source_file": "pkg/sync/checkpoint.go", "source_location": "L496", "weight": 1.0}, {"source": "sync_multipartuploadstore_ensuremultipartuploadstate", "target": "time", "relation": "references", "confidence": "EXTRACTED", "source_file": "pkg/sync/checkpoint.go", "source_location": "L496", "weight": 1.0, "context": "parameter_type"}, {"source": "sync_multipartuploadstore_ensuremultipartuploadstate", "target": "multipartupload", "relation": "references", "confidence": "EXTRACTED", "source_file": "pkg/sync/checkpoint.go", "source_location": "L496", "weight": 1.0, "context": "parameter_type"}, {"source": "sync_multipartuploadstore_ensuremultipartuploadstate", "target": "sync_multipartuploadstate", "relation": "references", "confidence": "EXTRACTED", "source_file": "pkg/sync/checkpoint.go", "source_location": "L496", "weight": 1.0, "context": "return_type"}, {"source": "sync_multipartuploadstore", "target": "sync_multipartuploadstore_markmultipartpart", "relation": "method", "confidence": "EXTRACTED", "source_file": "pkg/sync/checkpoint.go", "source_location": "L518", "weight": 1.0}, {"source": "sync_multipartuploadstore_markmultipartpart", "target": "sync_multipartuploadstate", "relation": "references", "confidence": "EXTRACTED", "source_file": "pkg/sync/checkpoint.go", "source_location": "L518", "weight": 1.0, "context": "parameter_type"}, {"source": "sync_multipartuploadstore_markmultipartpart", "target": "part", "relation": "references", "confidence": "EXTRACTED", "source_file": "pkg/sync/checkpoint.go", "source_location": "L518", "weight": 1.0, "context": "parameter_type"}, {"source": "sync_multipartuploadstore", "target": "sync_multipartuploadstore_getmultipartpart", "relation": "method", "confidence": "EXTRACTED", "source_file": "pkg/sync/checkpoint.go", "source_location": "L537", "weight": 1.0}, {"source": "sync_multipartuploadstore_getmultipartpart", "target": "sync_multipartuploadstate", "relation": "references", "confidence": "EXTRACTED", "source_file": "pkg/sync/checkpoint.go", "source_location": "L537", "weight": 1.0, "context": "parameter_type"}, {"source": "sync_multipartuploadstore_getmultipartpart", "target": "part", "relation": "references", "confidence": "EXTRACTED", "source_file": "pkg/sync/checkpoint.go", "source_location": "L537", "weight": 1.0, "context": "return_type"}, {"source": "sync_multipartuploadstore", "target": "sync_multipartuploadstore_finishmultipartupload", "relation": "method", "confidence": "EXTRACTED", "source_file": "pkg/sync/checkpoint.go", "source_location": "L557", "weight": 1.0}, {"source": "users_zhijian_golandprojects_juicefs_pkg_sync_checkpoint_go", "target": "sync_workermultipartuploads", "relation": "contains", "confidence": "EXTRACTED", "source_file": "pkg/sync/checkpoint.go", "source_location": "L563", "weight": 1.0}, {"source": "sync_workermultipartuploads", "target": "sync_multipartuploadstore", "relation": "embeds", "confidence": "EXTRACTED", "source_file": "pkg/sync/checkpoint.go", "source_location": "L564", "weight": 1.0}, {"source": "users_zhijian_golandprojects_juicefs_pkg_sync_checkpoint_go", "target": "users_zhijian_golandprojects_juicefs_pkg_sync_checkpoint_newworkermultipartuploads", "relation": "contains", "confidence": "EXTRACTED", "source_file": "pkg/sync/checkpoint.go", "source_location": "L568", "weight": 1.0}, {"source": "users_zhijian_golandprojects_juicefs_pkg_sync_checkpoint_newworkermultipartuploads", "target": "sync_workermultipartuploads", "relation": "references", "confidence": "EXTRACTED", "source_file": "pkg/sync/checkpoint.go", "source_location": "L568", "weight": 1.0, "context": "return_type"}, {"source": "sync_workermultipartuploads", "target": "sync_workermultipartuploads_markmultipartpart", "relation": "method", "confidence": "EXTRACTED", "source_file": "pkg/sync/checkpoint.go", "source_location": "L575", "weight": 1.0}, {"source": "sync_workermultipartuploads_markmultipartpart", "target": "sync_multipartuploadstate", "relation": "references", "confidence": "EXTRACTED", "source_file": "pkg/sync/checkpoint.go", "source_location": "L575", "weight": 1.0, "context": "parameter_type"}, {"source": "sync_workermultipartuploads_markmultipartpart", "target": "part", "relation": "references", "confidence": "EXTRACTED", "source_file": "pkg/sync/checkpoint.go", "source_location": "L575", "weight": 1.0, "context": "parameter_type"}, {"source": "sync_workermultipartuploads", "target": "sync_workermultipartuploads_finishmultipartupload", "relation": "method", "confidence": "EXTRACTED", "source_file": "pkg/sync/checkpoint.go", "source_location": "L601", "weight": 1.0}, {"source": "sync_checkpointmanager", "target": "sync_checkpointmanager_markcompleted", "relation": "method", "confidence": "EXTRACTED", "source_file": "pkg/sync/checkpoint.go", "source_location": "L609", "weight": 1.0}, {"source": "sync_checkpointmanager", "target": "sync_checkpointmanager_markfailed", "relation": "method", "confidence": "EXTRACTED", "source_file": "pkg/sync/checkpoint.go", "source_location": "L628", "weight": 1.0}, {"source": "sync_checkpointmanager", "target": "sync_checkpointmanager_addpendingkey", "relation": "method", "confidence": "EXTRACTED", "source_file": "pkg/sync/checkpoint.go", "source_location": "L648", "weight": 1.0}, {"source": "sync_checkpointmanager_addpendingkey", "target": "object", "relation": "references", "confidence": "EXTRACTED", "source_file": "pkg/sync/checkpoint.go", "source_location": "L648", "weight": 1.0, "context": "parameter_type"}, {"source": "sync_checkpointmanager", "target": "sync_checkpointmanager_updatelastlistedkey", "relation": "method", "confidence": "EXTRACTED", "source_file": "pkg/sync/checkpoint.go", "source_location": "L659", "weight": 1.0}, {"source": "sync_checkpointmanager_updatelastlistedkey", "target": "object", "relation": "references", "confidence": "EXTRACTED", "source_file": "pkg/sync/checkpoint.go", "source_location": "L659", "weight": 1.0, "context": "parameter_type"}, {"source": "sync_checkpointmanager", "target": "sync_checkpointmanager_trackkey", "relation": "method", "confidence": "EXTRACTED", "source_file": "pkg/sync/checkpoint.go", "source_location": "L668", "weight": 1.0}, {"source": "sync_checkpointmanager", "target": "sync_checkpointmanager_getlastlistedkey", "relation": "method", "confidence": "EXTRACTED", "source_file": "pkg/sync/checkpoint.go", "source_location": "L676", "weight": 1.0}, {"source": "sync_checkpointmanager", "target": "sync_checkpointmanager_restoreprefix", "relation": "method", "confidence": "EXTRACTED", "source_file": "pkg/sync/checkpoint.go", "source_location": "L692", "weight": 1.0}, {"source": "sync_checkpointmanager_restoreprefix", "target": "object", "relation": "references", "confidence": "EXTRACTED", "source_file": "pkg/sync/checkpoint.go", "source_location": "L692", "weight": 1.0, "context": "return_type"}, {"source": "sync_checkpointmanager", "target": "sync_checkpointmanager_listprefixes", "relation": "method", "confidence": "EXTRACTED", "source_file": "pkg/sync/checkpoint.go", "source_location": "L723", "weight": 1.0}, {"source": "sync_checkpointmanager", "target": "sync_checkpointmanager_registerchildprefix", "relation": "method", "confidence": "EXTRACTED", "source_file": "pkg/sync/checkpoint.go", "source_location": "L737", "weight": 1.0}, {"source": "sync_checkpointmanager", "target": "sync_checkpointmanager_stop", "relation": "method", "confidence": "EXTRACTED", "source_file": "pkg/sync/checkpoint.go", "source_location": "L747", "weight": 1.0}, {"source": "sync_checkpointmanager", "target": "sync_checkpointmanager_deletecheckpoint", "relation": "method", "confidence": "EXTRACTED", "source_file": "pkg/sync/checkpoint.go", "source_location": "L757", "weight": 1.0}, {"source": "sync_checkpointmanager", "target": "sync_checkpointmanager_reset", "relation": "method", "confidence": "EXTRACTED", "source_file": "pkg/sync/checkpoint.go", "source_location": "L764", "weight": 1.0}, {"source": "sync_checkpointmanager_reset", "target": "config", "relation": "references", "confidence": "EXTRACTED", "source_file": "pkg/sync/checkpoint.go", "source_location": "L764", "weight": 1.0, "context": "parameter_type"}, {"source": "sync_checkpointmanager", "target": "sync_checkpointmanager_startperiodicsave", "relation": "method", "confidence": "EXTRACTED", "source_file": "pkg/sync/checkpoint.go", "source_location": "L770", "weight": 1.0}, {"source": "sync_checkpointmanager_startperiodicsave", "target": "duration", "relation": "references", "confidence": "EXTRACTED", "source_file": "pkg/sync/checkpoint.go", "source_location": "L770", "weight": 1.0, "context": "parameter_type"}, {"source": "sync_checkpointmanager", "target": "sync_checkpointmanager_saveonsignal", "relation": "method", "confidence": "EXTRACTED", "source_file": "pkg/sync/checkpoint.go", "source_location": "L793", "weight": 1.0}, {"source": "users_zhijian_golandprojects_juicefs_pkg_sync_checkpoint_go", "target": "users_zhijian_golandprojects_juicefs_pkg_sync_checkpoint_trackcheckpointcompletion", "relation": "contains", "confidence": "EXTRACTED", "source_file": "pkg/sync/checkpoint.go", "source_location": "L813", "weight": 1.0}, {"source": "users_zhijian_golandprojects_juicefs_pkg_sync_checkpoint_trackcheckpointcompletion", "target": "sync_checkpointmanager", "relation": "references", "confidence": "EXTRACTED", "source_file": "pkg/sync/checkpoint.go", "source_location": "L813", "weight": 1.0, "context": "parameter_type"}, {"source": "users_zhijian_golandprojects_juicefs_pkg_sync_checkpoint_trackcheckpointcompletion", "target": "config", "relation": "references", "confidence": "EXTRACTED", "source_file": "pkg/sync/checkpoint.go", "source_location": "L813", "weight": 1.0, "context": "parameter_type"}, {"source": "users_zhijian_golandprojects_juicefs_pkg_sync_checkpoint_newcheckpointmanager", "target": "users_zhijian_golandprojects_juicefs_pkg_sync_checkpoint_newcheckpoint", "relation": "calls", "context": "call", "confidence": "EXTRACTED", "source_file": "pkg/sync/checkpoint.go", "source_location": "L170", "weight": 1.0}, {"source": "users_zhijian_golandprojects_juicefs_pkg_sync_checkpoint_newcheckpointmanager", "target": "users_zhijian_golandprojects_juicefs_pkg_sync_checkpoint_newmultipartuploadstore", "relation": "calls", "context": "call", "confidence": "EXTRACTED", "source_file": "pkg/sync/checkpoint.go", "source_location": "L172", "weight": 1.0}, {"source": "users_zhijian_golandprojects_juicefs_pkg_sync_checkpoint_newcheckpointmanager", "target": "users_zhijian_golandprojects_juicefs_pkg_sync_checkpoint_generatecheckpointkey", "relation": "calls", "context": "call", "confidence": "EXTRACTED", "source_file": "pkg/sync/checkpoint.go", "source_location": "L175", "weight": 1.0}, {"source": "sync_checkpointmanager_cleanupcheckpointtmp", "target": "users_zhijian_golandprojects_juicefs_pkg_sync_checkpoint_checkpointtmpprefix", "relation": "calls", "context": "call", "confidence": "EXTRACTED", "source_file": "pkg/sync/checkpoint.go", "source_location": "L220", "weight": 1.0}, {"source": "sync_checkpointmanager_load", "target": "sync_checkpointmanager_cleanupcheckpointtmp", "relation": "calls", "context": "call", "confidence": "EXTRACTED", "source_file": "pkg/sync/checkpoint.go", "source_location": "L239", "weight": 1.0}, {"source": "sync_checkpointmanager_load", "target": "sync_multipartuploadstore_reset", "relation": "calls", "context": "call", "confidence": "EXTRACTED", "source_file": "pkg/sync/checkpoint.go", "source_location": "L264", "weight": 1.0}, {"source": "sync_checkpointmanager_updateprefixstate", "target": "sync_checkpointmanager_getorcreateprefixstate", "relation": "calls", "context": "call", "confidence": "EXTRACTED", "source_file": "pkg/sync/checkpoint.go", "source_location": "L399", "weight": 1.0}, {"source": "sync_checkpointmanager_marklistdone", "target": "sync_checkpointmanager_updateprefixstate", "relation": "calls", "context": "call", "confidence": "EXTRACTED", "source_file": "pkg/sync/checkpoint.go", "source_location": "L417", "weight": 1.0}, {"source": "sync_multipartuploadstate_ismatched", "target": "sync_multipartuploadstate_isvalid", "relation": "calls", "context": "call", "confidence": "EXTRACTED", "source_file": "pkg/sync/checkpoint.go", "source_location": "L440", "weight": 1.0}, {"source": "sync_multipartuploadstore_findmultipartupload", "target": "sync_multipartuploadstate_ismatched", "relation": "calls", "context": "call", "confidence": "EXTRACTED", "source_file": "pkg/sync/checkpoint.go", "source_location": "L455", "weight": 1.0}, {"source": "sync_multipartuploadstore_getmultipartcheckpoint", "target": "sync_multipartuploadstate_ismatched", "relation": "calls", "context": "call", "confidence": "EXTRACTED", "source_file": "pkg/sync/checkpoint.go", "source_location": "L464", "weight": 1.0}, {"source": "sync_multipartuploadstore_putmultipartcheckpoint", "target": "sync_multipartuploadstate_isvalid", "relation": "calls", "context": "call", "confidence": "EXTRACTED", "source_file": "pkg/sync/checkpoint.go", "source_location": "L471", "weight": 1.0}, {"source": "sync_multipartuploadstore_ensuremultipartuploadstate", "target": "sync_multipartuploadstate_ismatched", "relation": "calls", "context": "call", "confidence": "EXTRACTED", "source_file": "pkg/sync/checkpoint.go", "source_location": "L502", "weight": 1.0}, {"source": "sync_multipartuploadstore_markmultipartpart", "target": "sync_multipartuploadstate_isvalid", "relation": "calls", "context": "call", "confidence": "EXTRACTED", "source_file": "pkg/sync/checkpoint.go", "source_location": "L519", "weight": 1.0}, {"source": "sync_multipartuploadstore_getmultipartpart", "target": "sync_multipartuploadstate_isvalid", "relation": "calls", "context": "call", "confidence": "EXTRACTED", "source_file": "pkg/sync/checkpoint.go", "source_location": "L538", "weight": 1.0}, {"source": "users_zhijian_golandprojects_juicefs_pkg_sync_checkpoint_newworkermultipartuploads", "target": "users_zhijian_golandprojects_juicefs_pkg_sync_checkpoint_newmultipartuploadstore", "relation": "calls", "context": "call", "confidence": "EXTRACTED", "source_file": "pkg/sync/checkpoint.go", "source_location": "L570", "weight": 1.0}, {"source": "sync_workermultipartuploads_markmultipartpart", "target": "sync_multipartuploadstate_isvalid", "relation": "calls", "context": "call", "confidence": "EXTRACTED", "source_file": "pkg/sync/checkpoint.go", "source_location": "L576", "weight": 1.0}, {"source": "sync_checkpointmanager_markcompleted", "target": "sync_workermultipartuploads_finishmultipartupload", "relation": "calls", "context": "call", "confidence": "EXTRACTED", "source_file": "pkg/sync/checkpoint.go", "source_location": "L615", "weight": 1.0}, {"source": "sync_checkpointmanager_markcompleted", "target": "sync_checkpointmanager_updateprefixstate", "relation": "calls", "context": "call", "confidence": "EXTRACTED", "source_file": "pkg/sync/checkpoint.go", "source_location": "L620", "weight": 1.0}, {"source": "sync_checkpointmanager_markfailed", "target": "sync_checkpointmanager_load", "relation": "calls", "context": "call", "confidence": "EXTRACTED", "source_file": "pkg/sync/checkpoint.go", "source_location": "L632", "weight": 1.0}, {"source": "sync_checkpointmanager_markfailed", "target": "sync_checkpointmanager_updateprefixstate", "relation": "calls", "context": "call", "confidence": "EXTRACTED", "source_file": "pkg/sync/checkpoint.go", "source_location": "L638", "weight": 1.0}, {"source": "sync_checkpointmanager_addpendingkey", "target": "sync_checkpointmanager_updateprefixstate", "relation": "calls", "context": "call", "confidence": "EXTRACTED", "source_file": "pkg/sync/checkpoint.go", "source_location": "L652", "weight": 1.0}, {"source": "sync_checkpointmanager_addpendingkey", "target": "sync_checkpointmanager_trackkey", "relation": "calls", "context": "call", "confidence": "EXTRACTED", "source_file": "pkg/sync/checkpoint.go", "source_location": "L656", "weight": 1.0}, {"source": "sync_checkpointmanager_updatelastlistedkey", "target": "sync_checkpointmanager_updateprefixstate", "relation": "calls", "context": "call", "confidence": "EXTRACTED", "source_file": "pkg/sync/checkpoint.go", "source_location": "L663", "weight": 1.0}, {"source": "sync_checkpointmanager_registerchildprefix", "target": "sync_checkpointmanager_getorcreateprefixstate", "relation": "calls", "context": "call", "confidence": "EXTRACTED", "source_file": "pkg/sync/checkpoint.go", "source_location": "L741", "weight": 1.0}, {"source": "sync_checkpointmanager_reset", "target": "users_zhijian_golandprojects_juicefs_pkg_sync_checkpoint_newcheckpoint", "relation": "calls", "context": "call", "confidence": "EXTRACTED", "source_file": "pkg/sync/checkpoint.go", "source_location": "L765", "weight": 1.0}, {"source": "sync_checkpointmanager_reset", "target": "sync_multipartuploadstore_reset", "relation": "calls", "context": "call", "confidence": "EXTRACTED", "source_file": "pkg/sync/checkpoint.go", "source_location": "L767", "weight": 1.0}, {"source": "sync_checkpointmanager_startperiodicsave", "target": "sync_checkpointmanager_stop", "relation": "calls", "context": "call", "confidence": "EXTRACTED", "source_file": "pkg/sync/checkpoint.go", "source_location": "L776", "weight": 1.0}, {"source": "sync_checkpointmanager_startperiodicsave", "target": "sync_checkpointmanager_save", "relation": "calls", "context": "call", "confidence": "EXTRACTED", "source_file": "pkg/sync/checkpoint.go", "source_location": "L781", "weight": 1.0}, {"source": "sync_checkpointmanager_saveonsignal", "target": "sync_checkpointmanager_stop", "relation": "calls", "context": "call", "confidence": "EXTRACTED", "source_file": "pkg/sync/checkpoint.go", "source_location": "L800", "weight": 1.0}, {"source": "sync_checkpointmanager_saveonsignal", "target": "sync_checkpointmanager_save", "relation": "calls", "context": "call", "confidence": "EXTRACTED", "source_file": "pkg/sync/checkpoint.go", "source_location": "L802", "weight": 1.0}, {"source": "users_zhijian_golandprojects_juicefs_pkg_sync_checkpoint_trackcheckpointcompletion", "target": "sync_checkpointmanager_markfailed", "relation": "calls", "context": "call", "confidence": "EXTRACTED", "source_file": "pkg/sync/checkpoint.go", "source_location": "L833", "weight": 1.0}, {"source": "users_zhijian_golandprojects_juicefs_pkg_sync_checkpoint_trackcheckpointcompletion", "target": "sync_checkpointmanager_markcompleted", "relation": "calls", "context": "call", "confidence": "EXTRACTED", "source_file": "pkg/sync/checkpoint.go", "source_location": "L835", "weight": 1.0}], "raw_calls": [{"caller_nid": "sync_prefixstate_marshaljson", "callee": "make", "is_member_call": false, "source_file": "pkg/sync/checkpoint.go", "source_location": "L67"}, {"caller_nid": "sync_prefixstate_marshaljson", "callee": "make", "is_member_call": false, "source_file": "pkg/sync/checkpoint.go", "source_location": "L68"}, {"caller_nid": "sync_prefixstate_marshaljson", "callee": "MarshalObject", "is_member_call": false, "source_file": "pkg/sync/checkpoint.go", "source_location": "L71"}, {"caller_nid": "sync_prefixstate_marshaljson", "callee": "MarshalObject", "is_member_call": false, "source_file": "pkg/sync/checkpoint.go", "source_location": "L74"}, {"caller_nid": "sync_prefixstate_marshaljson", "callee": "Marshal", "is_member_call": false, "source_file": "pkg/sync/checkpoint.go", "source_location": "L76"}, {"caller_nid": "sync_prefixstate_unmarshaljson", "callee": "Unmarshal", "is_member_call": false, "source_file": "pkg/sync/checkpoint.go", "source_location": "L81"}, {"caller_nid": "sync_prefixstate_unmarshaljson", "callee": "make", "is_member_call": false, "source_file": "pkg/sync/checkpoint.go", "source_location": "L87"}, {"caller_nid": "sync_prefixstate_unmarshaljson", "callee": "UnmarshalObject", "is_member_call": false, "source_file": "pkg/sync/checkpoint.go", "source_location": "L89"}, {"caller_nid": "sync_prefixstate_unmarshaljson", "callee": "make", "is_member_call": false, "source_file": "pkg/sync/checkpoint.go", "source_location": "L93"}, {"caller_nid": "sync_prefixstate_unmarshaljson", "callee": "UnmarshalObject", "is_member_call": false, "source_file": "pkg/sync/checkpoint.go", "source_location": "L95"}, {"caller_nid": "users_zhijian_golandprojects_juicefs_pkg_sync_checkpoint_newcheckpoint", "callee": "make", "is_member_call": false, "source_file": "pkg/sync/checkpoint.go", "source_location": "L161"}, {"caller_nid": "users_zhijian_golandprojects_juicefs_pkg_sync_checkpoint_newcheckpoint", "callee": "make", "is_member_call": false, "source_file": "pkg/sync/checkpoint.go", "source_location": "L162"}, {"caller_nid": "users_zhijian_golandprojects_juicefs_pkg_sync_checkpoint_newcheckpoint", "callee": "Now", "is_member_call": false, "source_file": "pkg/sync/checkpoint.go", "source_location": "L164"}, {"caller_nid": "users_zhijian_golandprojects_juicefs_pkg_sync_checkpoint_newcheckpointmanager", "callee": "DirStorage", "is_member_call": false, "source_file": "pkg/sync/checkpoint.go", "source_location": "L173"}, {"caller_nid": "users_zhijian_golandprojects_juicefs_pkg_sync_checkpoint_newcheckpointmanager", "callee": "make", "is_member_call": false, "source_file": "pkg/sync/checkpoint.go", "source_location": "L176"}, {"caller_nid": "users_zhijian_golandprojects_juicefs_pkg_sync_checkpoint_generatecheckpointkey", "callee": "New", "is_member_call": false, "source_file": "pkg/sync/checkpoint.go", "source_location": "L184"}, {"caller_nid": "users_zhijian_golandprojects_juicefs_pkg_sync_checkpoint_generatecheckpointkey", "callee": "Fprintf", "is_member_call": false, "source_file": "pkg/sync/checkpoint.go", "source_location": "L185"}, {"caller_nid": "users_zhijian_golandprojects_juicefs_pkg_sync_checkpoint_generatecheckpointkey", "callee": "Fprintf", "is_member_call": false, "source_file": "pkg/sync/checkpoint.go", "source_location": "L187"}, {"caller_nid": "users_zhijian_golandprojects_juicefs_pkg_sync_checkpoint_generatecheckpointkey", "callee": "Fprintf", "is_member_call": false, "source_file": "pkg/sync/checkpoint.go", "source_location": "L188"}, {"caller_nid": "users_zhijian_golandprojects_juicefs_pkg_sync_checkpoint_generatecheckpointkey", "callee": "Fprintf", "is_member_call": false, "source_file": "pkg/sync/checkpoint.go", "source_location": "L189"}, {"caller_nid": "users_zhijian_golandprojects_juicefs_pkg_sync_checkpoint_generatecheckpointkey", "callee": "Fprintf", "is_member_call": false, "source_file": "pkg/sync/checkpoint.go", "source_location": "L190"}, {"caller_nid": "users_zhijian_golandprojects_juicefs_pkg_sync_checkpoint_generatecheckpointkey", "callee": "Fprintf", "is_member_call": false, "source_file": "pkg/sync/checkpoint.go", "source_location": "L191"}, {"caller_nid": "users_zhijian_golandprojects_juicefs_pkg_sync_checkpoint_generatecheckpointkey", "callee": "Fprintf", "is_member_call": false, "source_file": "pkg/sync/checkpoint.go", "source_location": "L192"}, {"caller_nid": "users_zhijian_golandprojects_juicefs_pkg_sync_checkpoint_generatecheckpointkey", "callee": "Fprintf", "is_member_call": false, "source_file": "pkg/sync/checkpoint.go", "source_location": "L193"}, {"caller_nid": "users_zhijian_golandprojects_juicefs_pkg_sync_checkpoint_generatecheckpointkey", "callee": "Fprintf", "is_member_call": false, "source_file": "pkg/sync/checkpoint.go", "source_location": "L194"}, {"caller_nid": "users_zhijian_golandprojects_juicefs_pkg_sync_checkpoint_generatecheckpointkey", "callee": "Fprintf", "is_member_call": false, "source_file": "pkg/sync/checkpoint.go", "source_location": "L195"}, {"caller_nid": "users_zhijian_golandprojects_juicefs_pkg_sync_checkpoint_generatecheckpointkey", "callee": "Format", "is_member_call": true, "source_file": "pkg/sync/checkpoint.go", "source_location": "L195"}, {"caller_nid": "users_zhijian_golandprojects_juicefs_pkg_sync_checkpoint_generatecheckpointkey", "callee": "Format", "is_member_call": true, "source_file": "pkg/sync/checkpoint.go", "source_location": "L195"}, {"caller_nid": "users_zhijian_golandprojects_juicefs_pkg_sync_checkpoint_generatecheckpointkey", "callee": "Fprintf", "is_member_call": false, "source_file": "pkg/sync/checkpoint.go", "source_location": "L196"}, {"caller_nid": "users_zhijian_golandprojects_juicefs_pkg_sync_checkpoint_generatecheckpointkey", "callee": "Join", "is_member_call": false, "source_file": "pkg/sync/checkpoint.go", "source_location": "L196"}, {"caller_nid": "users_zhijian_golandprojects_juicefs_pkg_sync_checkpoint_generatecheckpointkey", "callee": "Join", "is_member_call": false, "source_file": "pkg/sync/checkpoint.go", "source_location": "L196"}, {"caller_nid": "users_zhijian_golandprojects_juicefs_pkg_sync_checkpoint_generatecheckpointkey", "callee": "Sum", "is_member_call": true, "source_file": "pkg/sync/checkpoint.go", "source_location": "L198"}, {"caller_nid": "users_zhijian_golandprojects_juicefs_pkg_sync_checkpoint_generatecheckpointkey", "callee": "Sprintf", "is_member_call": false, "source_file": "pkg/sync/checkpoint.go", "source_location": "L199"}, {"caller_nid": "users_zhijian_golandprojects_juicefs_pkg_sync_checkpoint_checkpointtmpprefix", "callee": "Base", "is_member_call": false, "source_file": "pkg/sync/checkpoint.go", "source_location": "L207"}, {"caller_nid": "users_zhijian_golandprojects_juicefs_pkg_sync_checkpoint_checkpointtmpprefix", "callee": "Dir", "is_member_call": false, "source_file": "pkg/sync/checkpoint.go", "source_location": "L212"}, {"caller_nid": "users_zhijian_golandprojects_juicefs_pkg_sync_checkpoint_checkpointtmpprefix", "callee": "Join", "is_member_call": false, "source_file": "pkg/sync/checkpoint.go", "source_location": "L216"}, {"caller_nid": "sync_checkpointmanager_cleanupcheckpointtmp", "callee": "ListAll", "is_member_call": false, "source_file": "pkg/sync/checkpoint.go", "source_location": "L221"}, {"caller_nid": "sync_checkpointmanager_cleanupcheckpointtmp", "callee": "Warnf", "is_member_call": true, "source_file": "pkg/sync/checkpoint.go", "source_location": "L223"}, {"caller_nid": "sync_checkpointmanager_cleanupcheckpointtmp", "callee": "Warnf", "is_member_call": true, "source_file": "pkg/sync/checkpoint.go", "source_location": "L228"}, {"caller_nid": "sync_checkpointmanager_cleanupcheckpointtmp", "callee": "Delete", "is_member_call": true, "source_file": "pkg/sync/checkpoint.go", "source_location": "L231"}, {"caller_nid": "sync_checkpointmanager_cleanupcheckpointtmp", "callee": "Key", "is_member_call": true, "source_file": "pkg/sync/checkpoint.go", "source_location": "L231"}, {"caller_nid": "sync_checkpointmanager_cleanupcheckpointtmp", "callee": "Warnf", "is_member_call": true, "source_file": "pkg/sync/checkpoint.go", "source_location": "L232"}, {"caller_nid": "sync_checkpointmanager_cleanupcheckpointtmp", "callee": "Key", "is_member_call": true, "source_file": "pkg/sync/checkpoint.go", "source_location": "L232"}, {"caller_nid": "sync_checkpointmanager_load", "callee": "Get", "is_member_call": true, "source_file": "pkg/sync/checkpoint.go", "source_location": "L240"}, {"caller_nid": "sync_checkpointmanager_load", "callee": "Head", "is_member_call": true, "source_file": "pkg/sync/checkpoint.go", "source_location": "L243"}, {"caller_nid": "sync_checkpointmanager_load", "callee": "IsNotExist", "is_member_call": false, "source_file": "pkg/sync/checkpoint.go", "source_location": "L243"}, {"caller_nid": "sync_checkpointmanager_load", "callee": "Close", "is_member_call": true, "source_file": "pkg/sync/checkpoint.go", "source_location": "L248"}, {"caller_nid": "sync_checkpointmanager_load", "callee": "ReadAll", "is_member_call": false, "source_file": "pkg/sync/checkpoint.go", "source_location": "L250"}, {"caller_nid": "sync_checkpointmanager_load", "callee": "Errorf", "is_member_call": false, "source_file": "pkg/sync/checkpoint.go", "source_location": "L252"}, {"caller_nid": "sync_checkpointmanager_load", "callee": "Unmarshal", "is_member_call": false, "source_file": "pkg/sync/checkpoint.go", "source_location": "L256"}, {"caller_nid": "sync_checkpointmanager_load", "callee": "Errorf", "is_member_call": false, "source_file": "pkg/sync/checkpoint.go", "source_location": "L257"}, {"caller_nid": "sync_checkpointmanager_load", "callee": "make", "is_member_call": false, "source_file": "pkg/sync/checkpoint.go", "source_location": "L260"}, {"caller_nid": "sync_checkpointmanager_save", "callee": "Lock", "is_member_call": true, "source_file": "pkg/sync/checkpoint.go", "source_location": "L273"}, {"caller_nid": "sync_checkpointmanager_save", "callee": "Unlock", "is_member_call": true, "source_file": "pkg/sync/checkpoint.go", "source_location": "L274"}, {"caller_nid": "sync_checkpointmanager_save", "callee": "statsUpdater", "is_member_call": true, "source_file": "pkg/sync/checkpoint.go", "source_location": "L276"}, {"caller_nid": "sync_checkpointmanager_save", "callee": "Now", "is_member_call": false, "source_file": "pkg/sync/checkpoint.go", "source_location": "L279"}, {"caller_nid": "sync_checkpointmanager_save", "callee": "RLock", "is_member_call": true, "source_file": "pkg/sync/checkpoint.go", "source_location": "L281"}, {"caller_nid": "sync_checkpointmanager_save", "callee": "RLock", "is_member_call": true, "source_file": "pkg/sync/checkpoint.go", "source_location": "L284"}, {"caller_nid": "sync_checkpointmanager_save", "callee": "RLock", "is_member_call": true, "source_file": "pkg/sync/checkpoint.go", "source_location": "L286"}, {"caller_nid": "sync_checkpointmanager_save", "callee": "Marshal", "is_member_call": false, "source_file": "pkg/sync/checkpoint.go", "source_location": "L287"}, {"caller_nid": "sync_checkpointmanager_save", "callee": "RUnlock", "is_member_call": true, "source_file": "pkg/sync/checkpoint.go", "source_location": "L288"}, {"caller_nid": "sync_checkpointmanager_save", "callee": "RUnlock", "is_member_call": true, "source_file": "pkg/sync/checkpoint.go", "source_location": "L290"}, {"caller_nid": "sync_checkpointmanager_save", "callee": "Lock", "is_member_call": true, "source_file": "pkg/sync/checkpoint.go", "source_location": "L292"}, {"caller_nid": "sync_checkpointmanager_save", "callee": "append", "is_member_call": false, "source_file": "pkg/sync/checkpoint.go", "source_location": "L293"}, {"caller_nid": "sync_checkpointmanager_save", "callee": "Unlock", "is_member_call": true, "source_file": "pkg/sync/checkpoint.go", "source_location": "L294"}, {"caller_nid": "sync_checkpointmanager_save", "callee": "Lock", "is_member_call": true, "source_file": "pkg/sync/checkpoint.go", "source_location": "L295"}, {"caller_nid": "sync_checkpointmanager_save", "callee": "append", "is_member_call": false, "source_file": "pkg/sync/checkpoint.go", "source_location": "L296"}, {"caller_nid": "sync_checkpointmanager_save", "callee": "Unlock", "is_member_call": true, "source_file": "pkg/sync/checkpoint.go", "source_location": "L297"}, {"caller_nid": "sync_checkpointmanager_save", "callee": "RUnlock", "is_member_call": true, "source_file": "pkg/sync/checkpoint.go", "source_location": "L298"}, {"caller_nid": "sync_checkpointmanager_save", "callee": "Errorf", "is_member_call": false, "source_file": "pkg/sync/checkpoint.go", "source_location": "L301"}, {"caller_nid": "sync_checkpointmanager_save", "callee": "Debugf", "is_member_call": true, "source_file": "pkg/sync/checkpoint.go", "source_location": "L304"}, {"caller_nid": "sync_checkpointmanager_save", "callee": "NewReader", "is_member_call": false, "source_file": "pkg/sync/checkpoint.go", "source_location": "L306"}, {"caller_nid": "sync_checkpointmanager_save", "callee": "Put", "is_member_call": true, "source_file": "pkg/sync/checkpoint.go", "source_location": "L307"}, {"caller_nid": "sync_checkpointmanager_save", "callee": "Errorf", "is_member_call": false, "source_file": "pkg/sync/checkpoint.go", "source_location": "L308"}, {"caller_nid": "sync_checkpointmanager_validateconfig", "callee": "Warnf", "is_member_call": true, "source_file": "pkg/sync/checkpoint.go", "source_location": "L320"}, {"caller_nid": "sync_checkpointmanager_validateconfig", "callee": "Equal", "is_member_call": false, "source_file": "pkg/sync/checkpoint.go", "source_location": "L324"}, {"caller_nid": "sync_checkpointmanager_validateconfig", "callee": "Equal", "is_member_call": false, "source_file": "pkg/sync/checkpoint.go", "source_location": "L324"}, {"caller_nid": "sync_checkpointmanager_validateconfig", "callee": "Warnf", "is_member_call": true, "source_file": "pkg/sync/checkpoint.go", "source_location": "L325"}, {"caller_nid": "sync_checkpointmanager_validateconfig", "callee": "Warnf", "is_member_call": true, "source_file": "pkg/sync/checkpoint.go", "source_location": "L330"}, {"caller_nid": "sync_checkpointmanager_validateconfig", "callee": "Warnf", "is_member_call": true, "source_file": "pkg/sync/checkpoint.go", "source_location": "L336"}, {"caller_nid": "sync_checkpointmanager_validateconfig", "callee": "Warnf", "is_member_call": true, "source_file": "pkg/sync/checkpoint.go", "source_location": "L342"}, {"caller_nid": "sync_checkpointmanager_validateconfig", "callee": "Warnf", "is_member_call": true, "source_file": "pkg/sync/checkpoint.go", "source_location": "L347"}, {"caller_nid": "sync_checkpointmanager_validateconfig", "callee": "Warnf", "is_member_call": true, "source_file": "pkg/sync/checkpoint.go", "source_location": "L353"}, {"caller_nid": "sync_checkpointmanager_validateconfig", "callee": "Warnf", "is_member_call": true, "source_file": "pkg/sync/checkpoint.go", "source_location": "L358"}, {"caller_nid": "sync_checkpointmanager_validateconfig", "callee": "Warnf", "is_member_call": true, "source_file": "pkg/sync/checkpoint.go", "source_location": "L363"}, {"caller_nid": "sync_checkpointmanager_validateconfig", "callee": "Warnf", "is_member_call": true, "source_file": "pkg/sync/checkpoint.go", "source_location": "L368"}, {"caller_nid": "sync_checkpointmanager_getorcreateprefixstate", "callee": "RLock", "is_member_call": true, "source_file": "pkg/sync/checkpoint.go", "source_location": "L377"}, {"caller_nid": "sync_checkpointmanager_getorcreateprefixstate", "callee": "RUnlock", "is_member_call": true, "source_file": "pkg/sync/checkpoint.go", "source_location": "L379"}, {"caller_nid": "sync_checkpointmanager_getorcreateprefixstate", "callee": "Lock", "is_member_call": true, "source_file": "pkg/sync/checkpoint.go", "source_location": "L384"}, {"caller_nid": "sync_checkpointmanager_getorcreateprefixstate", "callee": "Unlock", "is_member_call": true, "source_file": "pkg/sync/checkpoint.go", "source_location": "L385"}, {"caller_nid": "sync_checkpointmanager_getorcreateprefixstate", "callee": "make", "is_member_call": false, "source_file": "pkg/sync/checkpoint.go", "source_location": "L390"}, {"caller_nid": "sync_checkpointmanager_getorcreateprefixstate", "callee": "make", "is_member_call": false, "source_file": "pkg/sync/checkpoint.go", "source_location": "L391"}, {"caller_nid": "sync_checkpointmanager_updateprefixstate", "callee": "Lock", "is_member_call": true, "source_file": "pkg/sync/checkpoint.go", "source_location": "L401"}, {"caller_nid": "sync_checkpointmanager_updateprefixstate", "callee": "update", "is_member_call": false, "source_file": "pkg/sync/checkpoint.go", "source_location": "L402"}, {"caller_nid": "sync_checkpointmanager_updateprefixstate", "callee": "Unlock", "is_member_call": true, "source_file": "pkg/sync/checkpoint.go", "source_location": "L405"}, {"caller_nid": "sync_checkpointmanager_updateprefixstate", "callee": "Lock", "is_member_call": true, "source_file": "pkg/sync/checkpoint.go", "source_location": "L407"}, {"caller_nid": "sync_checkpointmanager_updateprefixstate", "callee": "delete", "is_member_call": false, "source_file": "pkg/sync/checkpoint.go", "source_location": "L408"}, {"caller_nid": "sync_checkpointmanager_updateprefixstate", "callee": "Unlock", "is_member_call": true, "source_file": "pkg/sync/checkpoint.go", "source_location": "L409"}, {"caller_nid": "users_zhijian_golandprojects_juicefs_pkg_sync_checkpoint_newmultipartuploadstore", "callee": "make", "is_member_call": false, "source_file": "pkg/sync/checkpoint.go", "source_location": "L429"}, {"caller_nid": "sync_multipartuploadstate_ismatched", "callee": "Equal", "is_member_call": true, "source_file": "pkg/sync/checkpoint.go", "source_location": "L440"}, {"caller_nid": "sync_multipartuploadstore_reset", "callee": "make", "is_member_call": false, "source_file": "pkg/sync/checkpoint.go", "source_location": "L445"}, {"caller_nid": "sync_multipartuploadstore_reset", "callee": "Lock", "is_member_call": true, "source_file": "pkg/sync/checkpoint.go", "source_location": "L447"}, {"caller_nid": "sync_multipartuploadstore_reset", "callee": "Unlock", "is_member_call": true, "source_file": "pkg/sync/checkpoint.go", "source_location": "L449"}, {"caller_nid": "sync_multipartuploadstore_findmultipartupload", "callee": "RLock", "is_member_call": true, "source_file": "pkg/sync/checkpoint.go", "source_location": "L453"}, {"caller_nid": "sync_multipartuploadstore_findmultipartupload", "callee": "RUnlock", "is_member_call": true, "source_file": "pkg/sync/checkpoint.go", "source_location": "L454"}, {"caller_nid": "sync_multipartuploadstore_getmultipartcheckpoint", "callee": "RLock", "is_member_call": true, "source_file": "pkg/sync/checkpoint.go", "source_location": "L462"}, {"caller_nid": "sync_multipartuploadstore_getmultipartcheckpoint", "callee": "RUnlock", "is_member_call": true, "source_file": "pkg/sync/checkpoint.go", "source_location": "L463"}, {"caller_nid": "sync_multipartuploadstore_putmultipartcheckpoint", "callee": "Lock", "is_member_call": true, "source_file": "pkg/sync/checkpoint.go", "source_location": "L474"}, {"caller_nid": "sync_multipartuploadstore_putmultipartcheckpoint", "callee": "Unlock", "is_member_call": true, "source_file": "pkg/sync/checkpoint.go", "source_location": "L475"}, {"caller_nid": "sync_multipartuploadstore_putmultipartcheckpoint", "callee": "make", "is_member_call": false, "source_file": "pkg/sync/checkpoint.go", "source_location": "L477"}, {"caller_nid": "sync_multipartuploadstore_putmultipartcheckpoint", "callee": "make", "is_member_call": false, "source_file": "pkg/sync/checkpoint.go", "source_location": "L485"}, {"caller_nid": "sync_multipartuploadstore_putmultipartcheckpoint", "callee": "Copy", "is_member_call": false, "source_file": "pkg/sync/checkpoint.go", "source_location": "L487"}, {"caller_nid": "sync_multipartuploadstore_putmultipartcheckpoint", "callee": "make", "is_member_call": false, "source_file": "pkg/sync/checkpoint.go", "source_location": "L490"}, {"caller_nid": "sync_multipartuploadstore_putmultipartcheckpoint", "callee": "Copy", "is_member_call": false, "source_file": "pkg/sync/checkpoint.go", "source_location": "L492"}, {"caller_nid": "sync_multipartuploadstore_ensuremultipartuploadstate", "callee": "Lock", "is_member_call": true, "source_file": "pkg/sync/checkpoint.go", "source_location": "L497"}, {"caller_nid": "sync_multipartuploadstore_ensuremultipartuploadstate", "callee": "Unlock", "is_member_call": true, "source_file": "pkg/sync/checkpoint.go", "source_location": "L498"}, {"caller_nid": "sync_multipartuploadstore_ensuremultipartuploadstate", "callee": "make", "is_member_call": false, "source_file": "pkg/sync/checkpoint.go", "source_location": "L500"}, {"caller_nid": "sync_multipartuploadstore_ensuremultipartuploadstate", "callee": "make", "is_member_call": false, "source_file": "pkg/sync/checkpoint.go", "source_location": "L511"}, {"caller_nid": "sync_multipartuploadstore_ensuremultipartuploadstate", "callee": "make", "is_member_call": false, "source_file": "pkg/sync/checkpoint.go", "source_location": "L512"}, {"caller_nid": "sync_multipartuploadstore_markmultipartpart", "callee": "Lock", "is_member_call": true, "source_file": "pkg/sync/checkpoint.go", "source_location": "L523"}, {"caller_nid": "sync_multipartuploadstore_markmultipartpart", "callee": "Unlock", "is_member_call": true, "source_file": "pkg/sync/checkpoint.go", "source_location": "L524"}, {"caller_nid": "sync_multipartuploadstore_markmultipartpart", "callee": "make", "is_member_call": false, "source_file": "pkg/sync/checkpoint.go", "source_location": "L526"}, {"caller_nid": "sync_multipartuploadstore_markmultipartpart", "callee": "make", "is_member_call": false, "source_file": "pkg/sync/checkpoint.go", "source_location": "L531"}, {"caller_nid": "sync_multipartuploadstore_getmultipartpart", "callee": "RLock", "is_member_call": true, "source_file": "pkg/sync/checkpoint.go", "source_location": "L541"}, {"caller_nid": "sync_multipartuploadstore_getmultipartpart", "callee": "RUnlock", "is_member_call": true, "source_file": "pkg/sync/checkpoint.go", "source_location": "L542"}, {"caller_nid": "sync_multipartuploadstore_finishmultipartupload", "callee": "Lock", "is_member_call": true, "source_file": "pkg/sync/checkpoint.go", "source_location": "L558"}, {"caller_nid": "sync_multipartuploadstore_finishmultipartupload", "callee": "Unlock", "is_member_call": true, "source_file": "pkg/sync/checkpoint.go", "source_location": "L559"}, {"caller_nid": "sync_multipartuploadstore_finishmultipartupload", "callee": "delete", "is_member_call": false, "source_file": "pkg/sync/checkpoint.go", "source_location": "L560"}, {"caller_nid": "users_zhijian_golandprojects_juicefs_pkg_sync_checkpoint_newworkermultipartuploads", "callee": "make", "is_member_call": false, "source_file": "pkg/sync/checkpoint.go", "source_location": "L571"}, {"caller_nid": "sync_workermultipartuploads_markmultipartpart", "callee": "Lock", "is_member_call": true, "source_file": "pkg/sync/checkpoint.go", "source_location": "L580"}, {"caller_nid": "sync_workermultipartuploads_markmultipartpart", "callee": "Unlock", "is_member_call": true, "source_file": "pkg/sync/checkpoint.go", "source_location": "L581"}, {"caller_nid": "sync_workermultipartuploads_markmultipartpart", "callee": "make", "is_member_call": false, "source_file": "pkg/sync/checkpoint.go", "source_location": "L583"}, {"caller_nid": "sync_workermultipartuploads_markmultipartpart", "callee": "make", "is_member_call": false, "source_file": "pkg/sync/checkpoint.go", "source_location": "L588"}, {"caller_nid": "sync_workermultipartuploads_markmultipartpart", "callee": "make", "is_member_call": false, "source_file": "pkg/sync/checkpoint.go", "source_location": "L593"}, {"caller_nid": "sync_workermultipartuploads_markmultipartpart", "callee": "make", "is_member_call": false, "source_file": "pkg/sync/checkpoint.go", "source_location": "L596"}, {"caller_nid": "sync_workermultipartuploads_finishmultipartupload", "callee": "Lock", "is_member_call": true, "source_file": "pkg/sync/checkpoint.go", "source_location": "L602"}, {"caller_nid": "sync_workermultipartuploads_finishmultipartupload", "callee": "Unlock", "is_member_call": true, "source_file": "pkg/sync/checkpoint.go", "source_location": "L603"}, {"caller_nid": "sync_workermultipartuploads_finishmultipartupload", "callee": "delete", "is_member_call": false, "source_file": "pkg/sync/checkpoint.go", "source_location": "L604"}, {"caller_nid": "sync_workermultipartuploads_finishmultipartupload", "callee": "delete", "is_member_call": false, "source_file": "pkg/sync/checkpoint.go", "source_location": "L605"}, {"caller_nid": "sync_checkpointmanager_markcompleted", "callee": "LoadAndDelete", "is_member_call": true, "source_file": "pkg/sync/checkpoint.go", "source_location": "L613"}, {"caller_nid": "sync_checkpointmanager_markcompleted", "callee": "delete", "is_member_call": false, "source_file": "pkg/sync/checkpoint.go", "source_location": "L621"}, {"caller_nid": "sync_checkpointmanager_markcompleted", "callee": "delete", "is_member_call": false, "source_file": "pkg/sync/checkpoint.go", "source_location": "L622"}, {"caller_nid": "sync_checkpointmanager_markfailed", "callee": "delete", "is_member_call": false, "source_file": "pkg/sync/checkpoint.go", "source_location": "L643"}, {"caller_nid": "sync_checkpointmanager_addpendingkey", "callee": "Key", "is_member_call": true, "source_file": "pkg/sync/checkpoint.go", "source_location": "L653"}, {"caller_nid": "sync_checkpointmanager_addpendingkey", "callee": "Key", "is_member_call": true, "source_file": "pkg/sync/checkpoint.go", "source_location": "L654"}, {"caller_nid": "sync_checkpointmanager_addpendingkey", "callee": "Key", "is_member_call": true, "source_file": "pkg/sync/checkpoint.go", "source_location": "L656"}, {"caller_nid": "sync_checkpointmanager_updatelastlistedkey", "callee": "Key", "is_member_call": true, "source_file": "pkg/sync/checkpoint.go", "source_location": "L664"}, {"caller_nid": "sync_checkpointmanager_trackkey", "callee": "Store", "is_member_call": true, "source_file": "pkg/sync/checkpoint.go", "source_location": "L672"}, {"caller_nid": "sync_checkpointmanager_getlastlistedkey", "callee": "RLock", "is_member_call": true, "source_file": "pkg/sync/checkpoint.go", "source_location": "L680"}, {"caller_nid": "sync_checkpointmanager_getlastlistedkey", "callee": "RUnlock", "is_member_call": true, "source_file": "pkg/sync/checkpoint.go", "source_location": "L682"}, {"caller_nid": "sync_checkpointmanager_getlastlistedkey", "callee": "RLock", "is_member_call": true, "source_file": "pkg/sync/checkpoint.go", "source_location": "L686"}, {"caller_nid": "sync_checkpointmanager_getlastlistedkey", "callee": "RUnlock", "is_member_call": true, "source_file": "pkg/sync/checkpoint.go", "source_location": "L687"}, {"caller_nid": "sync_checkpointmanager_restoreprefix", "callee": "RLock", "is_member_call": true, "source_file": "pkg/sync/checkpoint.go", "source_location": "L696"}, {"caller_nid": "sync_checkpointmanager_restoreprefix", "callee": "RUnlock", "is_member_call": true, "source_file": "pkg/sync/checkpoint.go", "source_location": "L698"}, {"caller_nid": "sync_checkpointmanager_restoreprefix", "callee": "LoadOrStore", "is_member_call": true, "source_file": "pkg/sync/checkpoint.go", "source_location": "L705"}, {"caller_nid": "sync_checkpointmanager_restoreprefix", "callee": "Lock", "is_member_call": true, "source_file": "pkg/sync/checkpoint.go", "source_location": "L708"}, {"caller_nid": "sync_checkpointmanager_restoreprefix", "callee": "Copy", "is_member_call": false, "source_file": "pkg/sync/checkpoint.go", "source_location": "L709"}, {"caller_nid": "sync_checkpointmanager_restoreprefix", "callee": "make", "is_member_call": false, "source_file": "pkg/sync/checkpoint.go", "source_location": "L710"}, {"caller_nid": "sync_checkpointmanager_restoreprefix", "callee": "make", "is_member_call": false, "source_file": "pkg/sync/checkpoint.go", "source_location": "L711"}, {"caller_nid": "sync_checkpointmanager_restoreprefix", "callee": "Store", "is_member_call": true, "source_file": "pkg/sync/checkpoint.go", "source_location": "L713"}, {"caller_nid": "sync_checkpointmanager_restoreprefix", "callee": "append", "is_member_call": false, "source_file": "pkg/sync/checkpoint.go", "source_location": "L714"}, {"caller_nid": "sync_checkpointmanager_restoreprefix", "callee": "Unlock", "is_member_call": true, "source_file": "pkg/sync/checkpoint.go", "source_location": "L718"}, {"caller_nid": "sync_checkpointmanager_listprefixes", "callee": "RLock", "is_member_call": true, "source_file": "pkg/sync/checkpoint.go", "source_location": "L727"}, {"caller_nid": "sync_checkpointmanager_listprefixes", "callee": "RUnlock", "is_member_call": true, "source_file": "pkg/sync/checkpoint.go", "source_location": "L728"}, {"caller_nid": "sync_checkpointmanager_listprefixes", "callee": "make", "is_member_call": false, "source_file": "pkg/sync/checkpoint.go", "source_location": "L729"}, {"caller_nid": "sync_checkpointmanager_listprefixes", "callee": "append", "is_member_call": false, "source_file": "pkg/sync/checkpoint.go", "source_location": "L731"}, {"caller_nid": "sync_checkpointmanager_registerchildprefix", "callee": "Lock", "is_member_call": true, "source_file": "pkg/sync/checkpoint.go", "source_location": "L742"}, {"caller_nid": "sync_checkpointmanager_registerchildprefix", "callee": "Unlock", "is_member_call": true, "source_file": "pkg/sync/checkpoint.go", "source_location": "L744"}, {"caller_nid": "sync_checkpointmanager_stop", "callee": "Do", "is_member_call": true, "source_file": "pkg/sync/checkpoint.go", "source_location": "L748"}, {"caller_nid": "sync_checkpointmanager_stop", "callee": "close", "is_member_call": false, "source_file": "pkg/sync/checkpoint.go", "source_location": "L749"}, {"caller_nid": "sync_checkpointmanager_deletecheckpoint", "callee": "Lock", "is_member_call": true, "source_file": "pkg/sync/checkpoint.go", "source_location": "L758"}, {"caller_nid": "sync_checkpointmanager_deletecheckpoint", "callee": "Unlock", "is_member_call": true, "source_file": "pkg/sync/checkpoint.go", "source_location": "L759"}, {"caller_nid": "sync_checkpointmanager_deletecheckpoint", "callee": "Delete", "is_member_call": true, "source_file": "pkg/sync/checkpoint.go", "source_location": "L760"}, {"caller_nid": "sync_checkpointmanager_startperiodicsave", "callee": "make", "is_member_call": false, "source_file": "pkg/sync/checkpoint.go", "source_location": "L771"}, {"caller_nid": "sync_checkpointmanager_startperiodicsave", "callee": "close", "is_member_call": false, "source_file": "pkg/sync/checkpoint.go", "source_location": "L774"}, {"caller_nid": "sync_checkpointmanager_startperiodicsave", "callee": "NewTicker", "is_member_call": false, "source_file": "pkg/sync/checkpoint.go", "source_location": "L775"}, {"caller_nid": "sync_checkpointmanager_startperiodicsave", "callee": "Errorf", "is_member_call": true, "source_file": "pkg/sync/checkpoint.go", "source_location": "L782"}, {"caller_nid": "sync_checkpointmanager_startperiodicsave", "callee": "Debugf", "is_member_call": true, "source_file": "pkg/sync/checkpoint.go", "source_location": "L784"}, {"caller_nid": "sync_checkpointmanager_startperiodicsave", "callee": "Format", "is_member_call": true, "source_file": "pkg/sync/checkpoint.go", "source_location": "L784"}, {"caller_nid": "sync_checkpointmanager_startperiodicsave", "callee": "Now", "is_member_call": false, "source_file": "pkg/sync/checkpoint.go", "source_location": "L784"}, {"caller_nid": "sync_checkpointmanager_saveonsignal", "callee": "make", "is_member_call": false, "source_file": "pkg/sync/checkpoint.go", "source_location": "L794"}, {"caller_nid": "sync_checkpointmanager_saveonsignal", "callee": "Notify", "is_member_call": false, "source_file": "pkg/sync/checkpoint.go", "source_location": "L795"}, {"caller_nid": "sync_checkpointmanager_saveonsignal", "callee": "Infof", "is_member_call": true, "source_file": "pkg/sync/checkpoint.go", "source_location": "L799"}, {"caller_nid": "sync_checkpointmanager_saveonsignal", "callee": "Errorf", "is_member_call": true, "source_file": "pkg/sync/checkpoint.go", "source_location": "L803"}, {"caller_nid": "sync_checkpointmanager_saveonsignal", "callee": "Infof", "is_member_call": true, "source_file": "pkg/sync/checkpoint.go", "source_location": "L805"}, {"caller_nid": "sync_checkpointmanager_saveonsignal", "callee": "Exit", "is_member_call": false, "source_file": "pkg/sync/checkpoint.go", "source_location": "L809"}, {"caller_nid": "users_zhijian_golandprojects_juicefs_pkg_sync_checkpoint_trackcheckpointcompletion", "callee": "Is", "is_member_call": false, "source_file": "pkg/sync/checkpoint.go", "source_location": "L818"}, {"caller_nid": "users_zhijian_golandprojects_juicefs_pkg_sync_checkpoint_trackcheckpointcompletion", "callee": "Lock", "is_member_call": true, "source_file": "pkg/sync/checkpoint.go", "source_location": "L822"}, {"caller_nid": "users_zhijian_golandprojects_juicefs_pkg_sync_checkpoint_trackcheckpointcompletion", "callee": "append", "is_member_call": false, "source_file": "pkg/sync/checkpoint.go", "source_location": "L824"}, {"caller_nid": "users_zhijian_golandprojects_juicefs_pkg_sync_checkpoint_trackcheckpointcompletion", "callee": "append", "is_member_call": false, "source_file": "pkg/sync/checkpoint.go", "source_location": "L826"}, {"caller_nid": "users_zhijian_golandprojects_juicefs_pkg_sync_checkpoint_trackcheckpointcompletion", "callee": "Unlock", "is_member_call": true, "source_file": "pkg/sync/checkpoint.go", "source_location": "L828"}]}