{"nodes": [{"id": "users_zhijian_golandprojects_juicefs_cmd_summary_go", "label": "summary.go", "file_type": "code", "source_file": "cmd/summary.go", "source_location": "L1"}, {"id": "users_zhijian_golandprojects_juicefs_cmd_summary_cmdsummary", "label": "cmdSummary()", "file_type": "code", "source_file": "cmd/summary.go", "source_location": "L35"}, {"id": "command", "label": "Command", "file_type": "code", "source_file": "", "source_location": "", "origin_file": "/Users/zhijian/GolandProjects/juicefs/cmd/summary.go"}, {"id": "users_zhijian_golandprojects_juicefs_cmd_summary_summary", "label": "summary()", "file_type": "code", "source_file": "cmd/summary.go", "source_location": "L83"}, {"id": "context", "label": "Context", "file_type": "code", "source_file": "", "source_location": "", "origin_file": "/Users/zhijian/GolandProjects/juicefs/cmd/summary.go"}, {"id": "users_zhijian_golandprojects_juicefs_cmd_summary_printcsvresult", "label": "printCSVResult()", "file_type": "code", "source_file": "cmd/summary.go", "source_location": "L163"}, {"id": "users_zhijian_golandprojects_juicefs_cmd_summary_rendertree", "label": "renderTree()", "file_type": "code", "source_file": "cmd/summary.go", "source_location": "L176"}, {"id": "treesummary", "label": "TreeSummary", "file_type": "code", "source_file": "", "source_location": "", "origin_file": "/Users/zhijian/GolandProjects/juicefs/cmd/summary.go"}], "edges": [{"source": "users_zhijian_golandprojects_juicefs_cmd_summary_go", "target": "go_pkg_encoding_csv", "relation": "imports_from", "confidence": "EXTRACTED", "source_file": "cmd/summary.go", "source_location": "L20", "weight": 1.0, "context": "import"}, {"source": "users_zhijian_golandprojects_juicefs_cmd_summary_go", "target": "go_pkg_encoding_json", "relation": "imports_from", "confidence": "EXTRACTED", "source_file": "cmd/summary.go", "source_location": "L21", "weight": 1.0, "context": "import"}, {"source": "users_zhijian_golandprojects_juicefs_cmd_summary_go", "target": "go_pkg_os", "relation": "imports_from", "confidence": "EXTRACTED", "source_file": "cmd/summary.go", "source_location": "L22", "weight": 1.0, "context": "import"}, {"source": "users_zhijian_golandprojects_juicefs_cmd_summary_go", "target": "go_pkg_path_filepath", "relation": "imports_from", "confidence": "EXTRACTED", "source_file": "cmd/summary.go", "source_location": "L23", "weight": 1.0, "context": "import"}, {"source": "users_zhijian_golandprojects_juicefs_cmd_summary_go", "target": "go_pkg_strconv", "relation": "imports_from", "confidence": "EXTRACTED", "source_file": "cmd/summary.go", "source_location": "L24", "weight": 1.0, "context": "import"}, {"source": "users_zhijian_golandprojects_juicefs_cmd_summary_go", "target": "go_pkg_strings", "relation": "imports_from", "confidence": "EXTRACTED", "source_file": "cmd/summary.go", "source_location": "L25", "weight": 1.0, "context": "import"}, {"source": "users_zhijian_golandprojects_juicefs_cmd_summary_go", "target": "go_pkg_syscall", "relation": "imports_from", "confidence": "EXTRACTED", "source_file": "cmd/summary.go", "source_location": "L26", "weight": 1.0, "context": "import"}, {"source": "users_zhijian_golandprojects_juicefs_cmd_summary_go", "target": "go_pkg_github_com_dustin_go_humanize", "relation": "imports_from", "confidence": "EXTRACTED", "source_file": "cmd/summary.go", "source_location": "L28", "weight": 1.0, "context": "import"}, {"source": "users_zhijian_golandprojects_juicefs_cmd_summary_go", "target": "go_pkg_github_com_juicedata_juicefs_pkg_meta", "relation": "imports_from", "confidence": "EXTRACTED", "source_file": "cmd/summary.go", "source_location": "L29", "weight": 1.0, "context": "import"}, {"source": "users_zhijian_golandprojects_juicefs_cmd_summary_go", "target": "go_pkg_github_com_juicedata_juicefs_pkg_utils", "relation": "imports_from", "confidence": "EXTRACTED", "source_file": "cmd/summary.go", "source_location": "L30", "weight": 1.0, "context": "import"}, {"source": "users_zhijian_golandprojects_juicefs_cmd_summary_go", "target": "go_pkg_github_com_juicedata_juicefs_pkg_vfs", "relation": "imports_from", "confidence": "EXTRACTED", "source_file": "cmd/summary.go", "source_location": "L31", "weight": 1.0, "context": "import"}, {"source": "users_zhijian_golandprojects_juicefs_cmd_summary_go", "target": "go_pkg_github_com_urfave_cli_v2", "relation": "imports_from", "confidence": "EXTRACTED", "source_file": "cmd/summary.go", "source_location": "L32", "weight": 1.0, "context": "import"}, {"source": "users_zhijian_golandprojects_juicefs_cmd_summary_go", "target": "users_zhijian_golandprojects_juicefs_cmd_summary_cmdsummary", "relation": "contains", "confidence": "EXTRACTED", "source_file": "cmd/summary.go", "source_location": "L35", "weight": 1.0}, {"source": "users_zhijian_golandprojects_juicefs_cmd_summary_cmdsummary", "target": "command", "relation": "references", "confidence": "EXTRACTED", "source_file": "cmd/summary.go", "source_location": "L35", "weight": 1.0, "context": "return_type"}, {"source": "users_zhijian_golandprojects_juicefs_cmd_summary_go", "target": "users_zhijian_golandprojects_juicefs_cmd_summary_summary", "relation": "contains", "confidence": "EXTRACTED", "source_file": "cmd/summary.go", "source_location": "L83", "weight": 1.0}, {"source": "users_zhijian_golandprojects_juicefs_cmd_summary_summary", "target": "context", "relation": "references", "confidence": "EXTRACTED", "source_file": "cmd/summary.go", "source_location": "L83", "weight": 1.0, "context": "parameter_type"}, {"source": "users_zhijian_golandprojects_juicefs_cmd_summary_go", "target": "users_zhijian_golandprojects_juicefs_cmd_summary_printcsvresult", "relation": "contains", "confidence": "EXTRACTED", "source_file": "cmd/summary.go", "source_location": "L163", "weight": 1.0}, {"source": "users_zhijian_golandprojects_juicefs_cmd_summary_go", "target": "users_zhijian_golandprojects_juicefs_cmd_summary_rendertree", "relation": "contains", "confidence": "EXTRACTED", "source_file": "cmd/summary.go", "source_location": "L176", "weight": 1.0}, {"source": "users_zhijian_golandprojects_juicefs_cmd_summary_rendertree", "target": "treesummary", "relation": "references", "confidence": "EXTRACTED", "source_file": "cmd/summary.go", "source_location": "L176", "weight": 1.0, "context": "parameter_type"}, {"source": "users_zhijian_golandprojects_juicefs_cmd_summary_summary", "target": "users_zhijian_golandprojects_juicefs_cmd_summary_rendertree", "relation": "calls", "context": "call", "confidence": "EXTRACTED", "source_file": "cmd/summary.go", "source_location": "L154", "weight": 1.0}, {"source": "users_zhijian_golandprojects_juicefs_cmd_summary_summary", "target": "users_zhijian_golandprojects_juicefs_cmd_summary_printcsvresult", "relation": "calls", "context": "call", "confidence": "EXTRACTED", "source_file": "cmd/summary.go", "source_location": "L156", "weight": 1.0}], "raw_calls": [{"caller_nid": "users_zhijian_golandprojects_juicefs_cmd_summary_summary", "callee": "setup", "is_member_call": false, "source_file": "cmd/summary.go", "source_location": "L84"}, {"caller_nid": "users_zhijian_golandprojects_juicefs_cmd_summary_summary", "callee": "Bool", "is_member_call": true, "source_file": "cmd/summary.go", "source_location": "L86"}, {"caller_nid": "users_zhijian_golandprojects_juicefs_cmd_summary_summary", "callee": "Uint", "is_member_call": true, "source_file": "cmd/summary.go", "source_location": "L89"}, {"caller_nid": "users_zhijian_golandprojects_juicefs_cmd_summary_summary", "callee": "Warn", "is_member_call": true, "source_file": "cmd/summary.go", "source_location": "L91"}, {"caller_nid": "users_zhijian_golandprojects_juicefs_cmd_summary_summary", "callee": "Uint", "is_member_call": true, "source_file": "cmd/summary.go", "source_location": "L94"}, {"caller_nid": "users_zhijian_golandprojects_juicefs_cmd_summary_summary", "callee": "Warn", "is_member_call": true, "source_file": "cmd/summary.go", "source_location": "L96"}, {"caller_nid": "users_zhijian_golandprojects_juicefs_cmd_summary_summary", "callee": "Bool", "is_member_call": true, "source_file": "cmd/summary.go", "source_location": "L100"}, {"caller_nid": "users_zhijian_golandprojects_juicefs_cmd_summary_summary", "callee": "NewProgress", "is_member_call": false, "source_file": "cmd/summary.go", "source_location": "L101"}, {"caller_nid": "users_zhijian_golandprojects_juicefs_cmd_summary_summary", "callee": "Get", "is_member_call": true, "source_file": "cmd/summary.go", "source_location": "L102"}, {"caller_nid": "users_zhijian_golandprojects_juicefs_cmd_summary_summary", "callee": "Args", "is_member_call": true, "source_file": "cmd/summary.go", "source_location": "L102"}, {"caller_nid": "users_zhijian_golandprojects_juicefs_cmd_summary_summary", "callee": "AddDoubleSpinner", "is_member_call": true, "source_file": "cmd/summary.go", "source_location": "L103"}, {"caller_nid": "users_zhijian_golandprojects_juicefs_cmd_summary_summary", "callee": "Abs", "is_member_call": false, "source_file": "cmd/summary.go", "source_location": "L104"}, {"caller_nid": "users_zhijian_golandprojects_juicefs_cmd_summary_summary", "callee": "Fatalf", "is_member_call": true, "source_file": "cmd/summary.go", "source_location": "L106"}, {"caller_nid": "users_zhijian_golandprojects_juicefs_cmd_summary_summary", "callee": "GetFileInode", "is_member_call": false, "source_file": "cmd/summary.go", "source_location": "L108"}, {"caller_nid": "users_zhijian_golandprojects_juicefs_cmd_summary_summary", "callee": "Fatalf", "is_member_call": true, "source_file": "cmd/summary.go", "source_location": "L110"}, {"caller_nid": "users_zhijian_golandprojects_juicefs_cmd_summary_summary", "callee": "uint64", "is_member_call": false, "source_file": "cmd/summary.go", "source_location": "L112"}, {"caller_nid": "users_zhijian_golandprojects_juicefs_cmd_summary_summary", "callee": "Fatalf", "is_member_call": true, "source_file": "cmd/summary.go", "source_location": "L113"}, {"caller_nid": "users_zhijian_golandprojects_juicefs_cmd_summary_summary", "callee": "openController", "is_member_call": false, "source_file": "cmd/summary.go", "source_location": "L115"}, {"caller_nid": "users_zhijian_golandprojects_juicefs_cmd_summary_summary", "callee": "Fatalf", "is_member_call": true, "source_file": "cmd/summary.go", "source_location": "L117"}, {"caller_nid": "users_zhijian_golandprojects_juicefs_cmd_summary_summary", "callee": "Close", "is_member_call": true, "source_file": "cmd/summary.go", "source_location": "L119"}, {"caller_nid": "users_zhijian_golandprojects_juicefs_cmd_summary_summary", "callee": "uint32", "is_member_call": false, "source_file": "cmd/summary.go", "source_location": "L120"}, {"caller_nid": "users_zhijian_golandprojects_juicefs_cmd_summary_summary", "callee": "uint32", "is_member_call": false, "source_file": "cmd/summary.go", "source_location": "L121"}, {"caller_nid": "users_zhijian_golandprojects_juicefs_cmd_summary_summary", "callee": "NewBuffer", "is_member_call": false, "source_file": "cmd/summary.go", "source_location": "L122"}, {"caller_nid": "users_zhijian_golandprojects_juicefs_cmd_summary_summary", "callee": "Put32", "is_member_call": true, "source_file": "cmd/summary.go", "source_location": "L123"}, {"caller_nid": "users_zhijian_golandprojects_juicefs_cmd_summary_summary", "callee": "Put32", "is_member_call": true, "source_file": "cmd/summary.go", "source_location": "L124"}, {"caller_nid": "users_zhijian_golandprojects_juicefs_cmd_summary_summary", "callee": "Put64", "is_member_call": true, "source_file": "cmd/summary.go", "source_location": "L125"}, {"caller_nid": "users_zhijian_golandprojects_juicefs_cmd_summary_summary", "callee": "Put8", "is_member_call": true, "source_file": "cmd/summary.go", "source_location": "L126"}, {"caller_nid": "users_zhijian_golandprojects_juicefs_cmd_summary_summary", "callee": "uint8", "is_member_call": false, "source_file": "cmd/summary.go", "source_location": "L126"}, {"caller_nid": "users_zhijian_golandprojects_juicefs_cmd_summary_summary", "callee": "Put8", "is_member_call": true, "source_file": "cmd/summary.go", "source_location": "L127"}, {"caller_nid": "users_zhijian_golandprojects_juicefs_cmd_summary_summary", "callee": "uint8", "is_member_call": false, "source_file": "cmd/summary.go", "source_location": "L127"}, {"caller_nid": "users_zhijian_golandprojects_juicefs_cmd_summary_summary", "callee": "Put8", "is_member_call": true, "source_file": "cmd/summary.go", "source_location": "L128"}, {"caller_nid": "users_zhijian_golandprojects_juicefs_cmd_summary_summary", "callee": "Write", "is_member_call": true, "source_file": "cmd/summary.go", "source_location": "L129"}, {"caller_nid": "users_zhijian_golandprojects_juicefs_cmd_summary_summary", "callee": "Bytes", "is_member_call": true, "source_file": "cmd/summary.go", "source_location": "L129"}, {"caller_nid": "users_zhijian_golandprojects_juicefs_cmd_summary_summary", "callee": "Fatalf", "is_member_call": true, "source_file": "cmd/summary.go", "source_location": "L131"}, {"caller_nid": "users_zhijian_golandprojects_juicefs_cmd_summary_summary", "callee": "readProgress", "is_member_call": false, "source_file": "cmd/summary.go", "source_location": "L133"}, {"caller_nid": "users_zhijian_golandprojects_juicefs_cmd_summary_summary", "callee": "SetCurrent", "is_member_call": true, "source_file": "cmd/summary.go", "source_location": "L134"}, {"caller_nid": "users_zhijian_golandprojects_juicefs_cmd_summary_summary", "callee": "int64", "is_member_call": false, "source_file": "cmd/summary.go", "source_location": "L134"}, {"caller_nid": "users_zhijian_golandprojects_juicefs_cmd_summary_summary", "callee": "int64", "is_member_call": false, "source_file": "cmd/summary.go", "source_location": "L134"}, {"caller_nid": "users_zhijian_golandprojects_juicefs_cmd_summary_summary", "callee": "Fatalf", "is_member_call": true, "source_file": "cmd/summary.go", "source_location": "L137"}, {"caller_nid": "users_zhijian_golandprojects_juicefs_cmd_summary_summary", "callee": "Errorf", "is_member_call": true, "source_file": "cmd/summary.go", "source_location": "L140"}, {"caller_nid": "users_zhijian_golandprojects_juicefs_cmd_summary_summary", "callee": "Errno", "is_member_call": false, "source_file": "cmd/summary.go", "source_location": "L140"}, {"caller_nid": "users_zhijian_golandprojects_juicefs_cmd_summary_summary", "callee": "Done", "is_member_call": true, "source_file": "cmd/summary.go", "source_location": "L142"}, {"caller_nid": "users_zhijian_golandprojects_juicefs_cmd_summary_summary", "callee": "Done", "is_member_call": true, "source_file": "cmd/summary.go", "source_location": "L143"}, {"caller_nid": "users_zhijian_golandprojects_juicefs_cmd_summary_summary", "callee": "Unmarshal", "is_member_call": false, "source_file": "cmd/summary.go", "source_location": "L146"}, {"caller_nid": "users_zhijian_golandprojects_juicefs_cmd_summary_summary", "callee": "Fatalf", "is_member_call": true, "source_file": "cmd/summary.go", "source_location": "L151"}, {"caller_nid": "users_zhijian_golandprojects_juicefs_cmd_summary_summary", "callee": "printResult", "is_member_call": false, "source_file": "cmd/summary.go", "source_location": "L158"}, {"caller_nid": "users_zhijian_golandprojects_juicefs_cmd_summary_printcsvresult", "callee": "NewWriter", "is_member_call": false, "source_file": "cmd/summary.go", "source_location": "L164"}, {"caller_nid": "users_zhijian_golandprojects_juicefs_cmd_summary_printcsvresult", "callee": "Write", "is_member_call": true, "source_file": "cmd/summary.go", "source_location": "L166"}, {"caller_nid": "users_zhijian_golandprojects_juicefs_cmd_summary_printcsvresult", "callee": "Fatalln", "is_member_call": true, "source_file": "cmd/summary.go", "source_location": "L167"}, {"caller_nid": "users_zhijian_golandprojects_juicefs_cmd_summary_printcsvresult", "callee": "Flush", "is_member_call": true, "source_file": "cmd/summary.go", "source_location": "L170"}, {"caller_nid": "users_zhijian_golandprojects_juicefs_cmd_summary_printcsvresult", "callee": "Fatal", "is_member_call": true, "source_file": "cmd/summary.go", "source_location": "L172"}, {"caller_nid": "users_zhijian_golandprojects_juicefs_cmd_summary_rendertree", "callee": "FormatUint", "is_member_call": false, "source_file": "cmd/summary.go", "source_location": "L182"}, {"caller_nid": "users_zhijian_golandprojects_juicefs_cmd_summary_rendertree", "callee": "IBytes", "is_member_call": true, "source_file": "cmd/summary.go", "source_location": "L184"}, {"caller_nid": "users_zhijian_golandprojects_juicefs_cmd_summary_rendertree", "callee": "uint64", "is_member_call": false, "source_file": "cmd/summary.go", "source_location": "L184"}, {"caller_nid": "users_zhijian_golandprojects_juicefs_cmd_summary_rendertree", "callee": "HasSuffix", "is_member_call": false, "source_file": "cmd/summary.go", "source_location": "L188"}, {"caller_nid": "users_zhijian_golandprojects_juicefs_cmd_summary_rendertree", "callee": "FormatUint", "is_member_call": false, "source_file": "cmd/summary.go", "source_location": "L195"}, {"caller_nid": "users_zhijian_golandprojects_juicefs_cmd_summary_rendertree", "callee": "FormatUint", "is_member_call": false, "source_file": "cmd/summary.go", "source_location": "L196"}, {"caller_nid": "users_zhijian_golandprojects_juicefs_cmd_summary_rendertree", "callee": "append", "is_member_call": false, "source_file": "cmd/summary.go", "source_location": "L198"}, {"caller_nid": "users_zhijian_golandprojects_juicefs_cmd_summary_rendertree", "callee": "renderTree", "is_member_call": false, "source_file": "cmd/summary.go", "source_location": "L200"}]}